{
  "generated_at": "2026-07-16T15:04:46",
  "data_source": "CBOE delayed (~15 min) + Finnhub (earnings/sector)",
  "config": {
    "min_weekly_yield": 0.7,
    "min_otm_pct": 5.0,
    "max_assign_prob": 20.0,
    "liquidity": {
      "min_oi": 500,
      "min_vol": 50,
      "max_spread_pct": 10.0
    },
    "cc_dte": [
      25,
      45
    ],
    "cc_min_weekly_yield": 0.5,
    "total_collateral": 120000.0,
    "per_name_cap_pct": 25.0,
    "per_sector_cap_pct": 30.0,
    "single_expiry_flag_pct": 50.0
  },
  "universe_size": 134,
  "earnings_source_ok": true,
  "result_count": 5,
  "results": [
    {
      "symbol": "INTC",
      "sector": "Semiconductors",
      "spot": 99.28,
      "strike": 85.0,
      "otm_pct": 14.4,
      "expiration": "2026-07-24",
      "dte": 8,
      "premium": 186.0,
      "weekly_yield": 1.915,
      "assign_pct": 17.9,
      "earnings_clear": true,
      "next_earnings": null,
      "wheel_ok": true,
      "cost_basis": 83.14,
      "cc_strike": 95.0,
      "cc_premium": 1365.0,
      "cc_expiration": "2026-08-21",
      "cc_dte": 36,
      "cc_weekly_yield": 3.192,
      "open_interest": 2025,
      "volume": 105,
      "spread_pct": 7.8,
      "iv": 124.5,
      "collateral": 8500.0,
      "score": 0.107,
      "tier": "yellow"
    },
    {
      "symbol": "MU",
      "sector": "Semiconductors",
      "spot": 864.79,
      "strike": 750.0,
      "otm_pct": 13.3,
      "expiration": "2026-07-24",
      "dte": 8,
      "premium": 1415.0,
      "weekly_yield": 1.651,
      "assign_pct": 17.6,
      "earnings_clear": true,
      "next_earnings": null,
      "wheel_ok": true,
      "cost_basis": 735.85,
      "cc_strike": 850.0,
      "cc_premium": 10995.0,
      "cc_expiration": "2026-08-21",
      "cc_dte": 36,
      "cc_weekly_yield": 2.905,
      "open_interest": 8417,
      "volume": 467,
      "spread_pct": 8.5,
      "iv": 112.2,
      "collateral": 75000.0,
      "score": 0.094,
      "tier": "yellow"
    },
    {
      "symbol": "NOW",
      "sector": "Technology",
      "spot": 100.88,
      "strike": 85.0,
      "otm_pct": 15.7,
      "expiration": "2026-07-24",
      "dte": 8,
      "premium": 106.0,
      "weekly_yield": 1.091,
      "assign_pct": 12.7,
      "earnings_clear": true,
      "next_earnings": null,
      "wheel_ok": true,
      "cost_basis": 83.94,
      "cc_strike": 100.0,
      "cc_premium": 960.0,
      "cc_expiration": "2026-08-21",
      "cc_dte": 36,
      "cc_weekly_yield": 2.224,
      "open_interest": 1737,
      "volume": 130,
      "spread_pct": 8.1,
      "iv": 107.8,
      "collateral": 8500.0,
      "score": 0.086,
      "tier": "yellow"
    },
    {
      "symbol": "AMD",
      "sector": "Semiconductors",
      "spot": 510.32,
      "strike": 450.0,
      "otm_pct": 11.8,
      "expiration": "2026-07-24",
      "dte": 8,
      "premium": 645.0,
      "weekly_yield": 1.254,
      "assign_pct": 16.8,
      "earnings_clear": true,
      "next_earnings": null,
      "wheel_ok": true,
      "cost_basis": 443.55,
      "cc_strike": 500.0,
      "cc_premium": 5805.0,
      "cc_expiration": "2026-08-21",
      "cc_dte": 36,
      "cc_weekly_yield": 2.545,
      "open_interest": 6131,
      "volume": 394,
      "spread_pct": 6.7,
      "iv": 93.2,
      "collateral": 45000.0,
      "score": 0.075,
      "tier": "yellow"
    },
    {
      "symbol": "SMCI",
      "sector": "Technology",
      "spot": 25.68,
      "strike": 23.0,
      "otm_pct": 10.4,
      "expiration": "2026-07-24",
      "dte": 8,
      "premium": 32.0,
      "weekly_yield": 1.217,
      "assign_pct": 17.8,
      "earnings_clear": true,
      "next_earnings": "2026-08-11",
      "wheel_ok": true,
      "cost_basis": 22.68,
      "cc_strike": 25.0,
      "cc_premium": 345.0,
      "cc_expiration": "2026-08-21",
      "cc_dte": 36,
      "cc_weekly_yield": 2.958,
      "open_interest": 979,
      "volume": 199,
      "spread_pct": 9.0,
      "iv": 85.7,
      "collateral": 2300.0,
      "score": 0.068,
      "tier": "yellow"
    }
  ],
  "indices": [
    {
      "label": "S&P 500",
      "value": 7567.75,
      "change_pct": -0.06
    },
    {
      "label": "Dow Jones",
      "value": 52754.0,
      "change_pct": 0.18
    },
    {
      "label": "Nasdaq 100",
      "value": 29263.81,
      "change_pct": -0.81
    }
  ]
}