{
  "generated_at": "2026-07-21T20:02:34",
  "data_source": "CBOE delayed (~15 min) + Finnhub (earnings/sector)",
  "config": {
    "min_weekly_yield": 0.7,
    "min_otm_pct": 5.0,
    "max_assign_prob": 20.0,
    "liquidity": {
      "min_oi": 500,
      "min_vol": 50,
      "max_spread_pct": 10.0
    },
    "cc_dte": [
      25,
      45
    ],
    "cc_min_weekly_yield": 0.5,
    "total_collateral": 120000.0,
    "per_name_cap_pct": 25.0,
    "per_sector_cap_pct": 30.0,
    "single_expiry_flag_pct": 50.0
  },
  "universe_size": 134,
  "earnings_source_ok": true,
  "result_count": 9,
  "results": [
    {
      "symbol": "INTC",
      "sector": "Semiconductors",
      "spot": 105.65,
      "strike": 90.0,
      "otm_pct": 14.8,
      "expiration": "2026-07-31",
      "dte": 10,
      "premium": 273.0,
      "weekly_yield": 2.123,
      "assign_pct": 19.8,
      "earnings_clear": true,
      "next_earnings": null,
      "wheel_ok": true,
      "cost_basis": 87.27,
      "cc_strike": 90.0,
      "cc_premium": 2105.0,
      "cc_expiration": "2026-08-21",
      "cc_dte": 31,
      "cc_weekly_yield": 5.447,
      "open_interest": 2809,
      "volume": 850,
      "spread_pct": 5.3,
      "iv": 131.2,
      "collateral": 9000.0,
      "score": 0.108,
      "tier": "yellow"
    },
    {
      "symbol": "NOW",
      "sector": "Technology",
      "spot": 101.74,
      "strike": 85.0,
      "otm_pct": 16.5,
      "expiration": "2026-07-31",
      "dte": 10,
      "premium": 120.0,
      "weekly_yield": 0.988,
      "assign_pct": 13.1,
      "earnings_clear": true,
      "next_earnings": null,
      "wheel_ok": true,
      "cost_basis": 83.8,
      "cc_strike": 85.0,
      "cc_premium": 1935.0,
      "cc_expiration": "2026-08-21",
      "cc_dte": 31,
      "cc_weekly_yield": 5.214,
      "open_interest": 876,
      "volume": 3230,
      "spread_pct": 5.7,
      "iv": 104.7,
      "collateral": 8500.0,
      "score": 0.076,
      "tier": "green"
    },
    {
      "symbol": "HOOD",
      "sector": "Financial Services",
      "spot": 106.34,
      "strike": 93.0,
      "otm_pct": 12.5,
      "expiration": "2026-07-31",
      "dte": 10,
      "premium": 172.0,
      "weekly_yield": 1.295,
      "assign_pct": 18.0,
      "earnings_clear": true,
      "next_earnings": null,
      "wheel_ok": true,
      "cost_basis": 91.28,
      "cc_strike": 100.0,
      "cc_premium": 1300.0,
      "cc_expiration": "2026-08-21",
      "cc_dte": 31,
      "cc_weekly_yield": 3.216,
      "open_interest": 1991,
      "volume": 196,
      "spread_pct": 6.2,
      "iv": 96.8,
      "collateral": 9300.0,
      "score": 0.072,
      "tier": "yellow"
    },
    {
      "symbol": "SMCI",
      "sector": "Technology",
      "spot": 25.23,
      "strike": 22.0,
      "otm_pct": 12.8,
      "expiration": "2026-07-31",
      "dte": 10,
      "premium": 39.0,
      "weekly_yield": 1.241,
      "assign_pct": 17.5,
      "earnings_clear": true,
      "next_earnings": null,
      "wheel_ok": true,
      "cost_basis": 21.61,
      "cc_strike": 24.0,
      "cc_premium": 370.0,
      "cc_expiration": "2026-08-21",
      "cc_dte": 31,
      "cc_weekly_yield": 3.866,
      "open_interest": 1092,
      "volume": 65,
      "spread_pct": 7.4,
      "iv": 96.6,
      "collateral": 2200.0,
      "score": 0.071,
      "tier": "yellow"
    },
    {
      "symbol": "AMD",
      "sector": "Semiconductors",
      "spot": 541.79,
      "strike": 480.0,
      "otm_pct": 11.4,
      "expiration": "2026-07-31",
      "dte": 10,
      "premium": 910.0,
      "weekly_yield": 1.327,
      "assign_pct": 19.1,
      "earnings_clear": true,
      "next_earnings": null,
      "wheel_ok": true,
      "cost_basis": 470.9,
      "cc_strike": 480.0,
      "cc_premium": 8855.0,
      "cc_expiration": "2026-08-21",
      "cc_dte": 31,
      "cc_weekly_yield": 4.246,
      "open_interest": 1069,
      "volume": 663,
      "spread_pct": 3.8,
      "iv": 92.1,
      "collateral": 48000.0,
      "score": 0.07,
      "tier": "yellow"
    },
    {
      "symbol": "WDC",
      "sector": "Technology",
      "spot": 545.74,
      "strike": 400.0,
      "otm_pct": 26.7,
      "expiration": "2026-08-21",
      "dte": 31,
      "premium": 1655.0,
      "weekly_yield": 0.934,
      "assign_pct": 14.5,
      "earnings_clear": true,
      "next_earnings": null,
      "wheel_ok": true,
      "cost_basis": 383.45,
      "cc_strike": 600.0,
      "cc_premium": 4870.0,
      "cc_expiration": "2026-08-21",
      "cc_dte": 31,
      "cc_weekly_yield": 2.868,
      "open_interest": 1217,
      "volume": 267,
      "spread_pct": 4.4,
      "iv": 122.3,
      "collateral": 40000.0,
      "score": 0.065,
      "tier": "green"
    },
    {
      "symbol": "TSM",
      "sector": "Semiconductors",
      "spot": 424.69,
      "strike": 390.0,
      "otm_pct": 8.2,
      "expiration": "2026-07-31",
      "dte": 10,
      "premium": 445.0,
      "weekly_yield": 0.799,
      "assign_pct": 18.7,
      "earnings_clear": true,
      "next_earnings": null,
      "wheel_ok": true,
      "cost_basis": 385.55,
      "cc_strike": 390.0,
      "cc_premium": 4630.0,
      "cc_expiration": "2026-08-21",
      "cc_dte": 31,
      "cc_weekly_yield": 2.712,
      "open_interest": 1031,
      "volume": 590,
      "spread_pct": 8.6,
      "iv": 62.0,
      "collateral": 39000.0,
      "score": 0.043,
      "tier": "yellow"
    },
    {
      "symbol": "DELL",
      "sector": "Technology",
      "spot": 402.5,
      "strike": 330.0,
      "otm_pct": 18.0,
      "expiration": "2026-08-21",
      "dte": 31,
      "premium": 1075.0,
      "weekly_yield": 0.736,
      "assign_pct": 17.8,
      "earnings_clear": true,
      "next_earnings": "2026-09-03",
      "wheel_ok": true,
      "cost_basis": 319.25,
      "cc_strike": 400.0,
      "cc_premium": 4045.0,
      "cc_expiration": "2026-08-21",
      "cc_dte": 31,
      "cc_weekly_yield": 2.861,
      "open_interest": 1201,
      "volume": 93,
      "spread_pct": 6.3,
      "iv": 87.1,
      "collateral": 33000.0,
      "score": 0.041,
      "tier": "yellow"
    },
    {
      "symbol": "GOOGL",
      "sector": "Media",
      "spot": 348.98,
      "strike": 325.0,
      "otm_pct": 6.9,
      "expiration": "2026-07-31",
      "dte": 10,
      "premium": 325.0,
      "weekly_yield": 0.7,
      "assign_pct": 19.5,
      "earnings_clear": true,
      "next_earnings": null,
      "wheel_ok": true,
      "cost_basis": 321.75,
      "cc_strike": 345.0,
      "cc_premium": 1840.0,
      "cc_expiration": "2026-08-21",
      "cc_dte": 31,
      "cc_weekly_yield": 1.291,
      "open_interest": 506,
      "volume": 435,
      "spread_pct": 8.8,
      "iv": 53.0,
      "collateral": 32500.0,
      "score": 0.036,
      "tier": "yellow"
    }
  ],
  "indices": [
    {
      "label": "S&P 500",
      "value": 7510.06,
      "change_pct": 0.9
    },
    {
      "label": "Dow Jones",
      "value": 52203.0,
      "change_pct": 0.7
    },
    {
      "label": "Nasdaq 100",
      "value": 29162.09,
      "change_pct": 1.95
    }
  ]
}