{
  "generated_at": "2026-07-06T18:28:27",
  "data_source": "CBOE delayed (~15 min) + Finnhub (earnings/sector)",
  "config": {
    "min_weekly_yield": 0.7,
    "min_otm_pct": 5.0,
    "max_assign_prob": 20.0,
    "liquidity": {
      "min_oi": 500,
      "min_vol": 50,
      "max_spread_pct": 10.0
    },
    "cc_dte": [
      25,
      45
    ],
    "cc_min_weekly_yield": 0.5,
    "total_collateral": 120000.0,
    "per_name_cap_pct": 25.0,
    "per_sector_cap_pct": 30.0,
    "single_expiry_flag_pct": 50.0
  },
  "universe_size": 134,
  "earnings_source_ok": true,
  "result_count": 4,
  "results": [
    {
      "symbol": "AMD",
      "sector": "Semiconductors",
      "spot": 556.05,
      "strike": 490.0,
      "otm_pct": 11.9,
      "expiration": "2026-07-17",
      "dte": 11,
      "premium": 810.0,
      "weekly_yield": 1.052,
      "assign_pct": 17.6,
      "earnings_clear": true,
      "next_earnings": null,
      "wheel_ok": true,
      "cost_basis": 481.9,
      "cc_strike": 520.0,
      "cc_premium": 6685.0,
      "cc_expiration": "2026-07-31",
      "cc_dte": 25,
      "cc_weekly_yield": 3.884,
      "open_interest": 2406,
      "volume": 750,
      "spread_pct": 4.8,
      "iv": 85.2,
      "collateral": 49000.0,
      "score": 0.06,
      "tier": "yellow"
    },
    {
      "symbol": "SMCI",
      "sector": "Technology",
      "spot": 26.95,
      "strike": 22.0,
      "otm_pct": 18.4,
      "expiration": "2026-07-24",
      "dte": 18,
      "premium": 42.0,
      "weekly_yield": 0.742,
      "assign_pct": 14.0,
      "earnings_clear": true,
      "next_earnings": null,
      "wheel_ok": true,
      "cost_basis": 21.58,
      "cc_strike": 27.0,
      "cc_premium": 258.0,
      "cc_expiration": "2026-07-31",
      "cc_dte": 25,
      "cc_weekly_yield": 3.348,
      "open_interest": 813,
      "volume": 51,
      "spread_pct": 9.1,
      "iv": 94.0,
      "collateral": 2200.0,
      "score": 0.053,
      "tier": "yellow"
    },
    {
      "symbol": "ANET",
      "sector": "Communications",
      "spot": 171.89,
      "strike": 155.0,
      "otm_pct": 9.8,
      "expiration": "2026-07-17",
      "dte": 11,
      "premium": 194.0,
      "weekly_yield": 0.796,
      "assign_pct": 17.3,
      "earnings_clear": true,
      "next_earnings": null,
      "wheel_ok": true,
      "cost_basis": 153.06,
      "cc_strike": 180.0,
      "cc_premium": 770.0,
      "cc_expiration": "2026-07-31",
      "cc_dte": 25,
      "cc_weekly_yield": 1.409,
      "open_interest": 2925,
      "volume": 558,
      "spread_pct": 6.5,
      "iv": 68.4,
      "collateral": 15500.0,
      "score": 0.046,
      "tier": "yellow"
    },
    {
      "symbol": "TSM",
      "sector": "Semiconductors",
      "spot": 454.31,
      "strike": 410.0,
      "otm_pct": 9.8,
      "expiration": "2026-07-17",
      "dte": 11,
      "premium": 515.0,
      "weekly_yield": 0.799,
      "assign_pct": 17.6,
      "earnings_clear": true,
      "next_earnings": null,
      "wheel_ok": true,
      "cost_basis": 404.85,
      "cc_strike": 455.0,
      "cc_premium": 2700.0,
      "cc_expiration": "2026-07-31",
      "cc_dte": 25,
      "cc_weekly_yield": 1.867,
      "open_interest": 10898,
      "volume": 626,
      "spread_pct": 6.6,
      "iv": 68.0,
      "collateral": 41000.0,
      "score": 0.045,
      "tier": "yellow"
    }
  ],
  "indices": []
}