{
  "generated_at": "2026-07-01T17:59:13",
  "data_source": "CBOE delayed (~15 min) + Finnhub (earnings/sector)",
  "config": {
    "min_weekly_yield": 0.7,
    "min_otm_pct": 5.0,
    "max_assign_prob": 20.0,
    "liquidity": {
      "min_oi": 500,
      "min_vol": 50,
      "max_spread_pct": 10.0
    },
    "cc_dte": [
      25,
      45
    ],
    "cc_min_weekly_yield": 0.5,
    "total_collateral": 120000.0,
    "per_name_cap_pct": 25.0,
    "per_sector_cap_pct": 30.0,
    "single_expiry_flag_pct": 50.0
  },
  "universe_size": 134,
  "earnings_source_ok": true,
  "result_count": 5,
  "results": [
    {
      "symbol": "MU",
      "sector": "Semiconductors",
      "spot": 1047.2,
      "strike": 820.0,
      "otm_pct": 21.7,
      "expiration": "2026-07-10",
      "dte": 9,
      "premium": 825.0,
      "weekly_yield": 0.783,
      "assign_pct": 8.6,
      "earnings_clear": true,
      "next_earnings": null,
      "wheel_ok": true,
      "cost_basis": 811.75,
      "cc_strike": 1200.0,
      "cc_premium": 6200.0,
      "cc_expiration": "2026-07-31",
      "cc_dte": 30,
      "cc_weekly_yield": 1.782,
      "open_interest": 513,
      "volume": 205,
      "spread_pct": 5.9,
      "iv": 122.0,
      "collateral": 82000.0,
      "score": 0.091,
      "tier": "yellow"
    },
    {
      "symbol": "INTC",
      "sector": "Semiconductors",
      "spot": 128.15,
      "strike": 115.0,
      "otm_pct": 10.3,
      "expiration": "2026-07-10",
      "dte": 9,
      "premium": 192.0,
      "weekly_yield": 1.299,
      "assign_pct": 19.3,
      "earnings_clear": true,
      "next_earnings": null,
      "wheel_ok": true,
      "cost_basis": 113.08,
      "cc_strike": 125.0,
      "cc_premium": 1520.0,
      "cc_expiration": "2026-07-31",
      "cc_dte": 30,
      "cc_weekly_yield": 3.136,
      "open_interest": 2445,
      "volume": 1132,
      "spread_pct": 4.1,
      "iv": 86.2,
      "collateral": 11500.0,
      "score": 0.067,
      "tier": "yellow"
    },
    {
      "symbol": "SMCI",
      "sector": "Technology",
      "spot": 28.33,
      "strike": 25.0,
      "otm_pct": 11.8,
      "expiration": "2026-07-10",
      "dte": 9,
      "premium": 37.0,
      "weekly_yield": 1.151,
      "assign_pct": 17.1,
      "earnings_clear": true,
      "next_earnings": null,
      "wheel_ok": true,
      "cost_basis": 24.63,
      "cc_strike": 29.0,
      "cc_premium": 255.0,
      "cc_expiration": "2026-07-31",
      "cc_dte": 30,
      "cc_weekly_yield": 2.416,
      "open_interest": 2036,
      "volume": 4436,
      "spread_pct": 7.8,
      "iv": 89.6,
      "collateral": 2500.0,
      "score": 0.067,
      "tier": "yellow"
    },
    {
      "symbol": "AMD",
      "sector": "Semiconductors",
      "spot": 552.41,
      "strike": 500.0,
      "otm_pct": 9.5,
      "expiration": "2026-07-10",
      "dte": 9,
      "premium": 605.0,
      "weekly_yield": 0.941,
      "assign_pct": 17.5,
      "earnings_clear": true,
      "next_earnings": null,
      "wheel_ok": true,
      "cost_basis": 493.95,
      "cc_strike": 600.0,
      "cc_premium": 2835.0,
      "cc_expiration": "2026-07-31",
      "cc_dte": 30,
      "cc_weekly_yield": 1.339,
      "open_interest": 1137,
      "volume": 794,
      "spread_pct": 6.4,
      "iv": 72.7,
      "collateral": 50000.0,
      "score": 0.054,
      "tier": "yellow"
    },
    {
      "symbol": "RIVN",
      "sector": "Automobiles",
      "spot": 17.52,
      "strike": 16.0,
      "otm_pct": 8.6,
      "expiration": "2026-07-10",
      "dte": 9,
      "premium": 18.0,
      "weekly_yield": 0.875,
      "assign_pct": 17.9,
      "earnings_clear": true,
      "next_earnings": null,
      "wheel_ok": true,
      "cost_basis": 15.82,
      "cc_strike": 17.0,
      "cc_premium": 167.0,
      "cc_expiration": "2026-07-31",
      "cc_dte": 30,
      "cc_weekly_yield": 2.463,
      "open_interest": 800,
      "volume": 391,
      "spread_pct": 5.4,
      "iv": 66.6,
      "collateral": 1600.0,
      "score": 0.049,
      "tier": "yellow"
    }
  ],
  "indices": [
    {
      "label": "S&P 500",
      "value": 7503.89,
      "change_pct": 0.06
    },
    {
      "label": "Dow Jones",
      "value": 52455.0,
      "change_pct": 0.26
    },
    {
      "label": "Nasdaq 100",
      "value": 29919.19,
      "change_pct": -1.18
    }
  ]
}