{
  "generated_at": "2026-06-17T16:41:29",
  "data_source": "CBOE delayed (~15 min) + Finnhub (earnings/sector)",
  "config": {
    "min_weekly_yield": 0.7,
    "min_otm_pct": 5.0,
    "max_assign_prob": 20.0,
    "liquidity": {
      "min_oi": 500,
      "min_vol": 50,
      "max_spread_pct": 10.0
    },
    "cc_dte": [
      25,
      45
    ],
    "cc_min_weekly_yield": 0.5,
    "total_collateral": 120000.0,
    "per_name_cap_pct": 25.0,
    "per_sector_cap_pct": 30.0,
    "single_expiry_flag_pct": 50.0
  },
  "universe_size": 134,
  "earnings_source_ok": true,
  "result_count": 2,
  "results": [
    {
      "symbol": "SMCI",
      "sector": "Technology",
      "spot": 29.11,
      "strike": 26.0,
      "otm_pct": 10.7,
      "expiration": "2026-06-26",
      "dte": 9,
      "premium": 33.0,
      "weekly_yield": 0.987,
      "assign_pct": 16.6,
      "earnings_clear": true,
      "next_earnings": "2026-08-03",
      "wheel_ok": true,
      "cost_basis": 25.67,
      "cc_strike": 28.0,
      "cc_premium": 320.0,
      "cc_expiration": "2026-07-17",
      "cc_dte": 30,
      "cc_weekly_yield": 2.909,
      "open_interest": 787,
      "volume": 80,
      "spread_pct": 8.7,
      "iv": 79.7,
      "collateral": 2600.0,
      "score": 0.059,
      "tier": "yellow"
    },
    {
      "symbol": "AMD",
      "sector": "Semiconductors",
      "spot": 523.18,
      "strike": 475.0,
      "otm_pct": 9.2,
      "expiration": "2026-06-26",
      "dte": 9,
      "premium": 645.0,
      "weekly_yield": 1.056,
      "assign_pct": 18.7,
      "earnings_clear": true,
      "next_earnings": "2026-08-03",
      "wheel_ok": true,
      "cost_basis": 468.55,
      "cc_strike": 500.0,
      "cc_premium": 5455.0,
      "cc_expiration": "2026-07-17",
      "cc_dte": 30,
      "cc_weekly_yield": 2.717,
      "open_interest": 524,
      "volume": 148,
      "spread_pct": 5.3,
      "iv": 74.2,
      "collateral": 47500.0,
      "score": 0.056,
      "tier": "yellow"
    }
  ],
  "indices": [
    {
      "label": "S&P 500",
      "value": 7518.4,
      "change_pct": 0.09
    },
    {
      "label": "Dow Jones",
      "value": 52225.0,
      "change_pct": 0.43
    },
    {
      "label": "Nasdaq 100",
      "value": 30128.09,
      "change_pct": 0.53
    }
  ]
}