{
  "generated_at": "2026-06-24T17:56:13",
  "data_source": "CBOE delayed (~15 min)",
  "account_picks": [
    {
      "account": "Account #1",
      "pick": {
        "symbol": "INTC",
        "preferred": true,
        "company_name": "Intel Corporation",
        "price": 130.32,
        "expiration": "2026-07-02",
        "dte": 8,
        "strike": 107.0,
        "bid": 0.83,
        "premium": 83.0,
        "pct_of_collateral": 0.776,
        "delta": -0.089,
        "open_interest": 452,
        "collateral": 10700.0,
        "contracts": 2,
        "total_premium": 166.0,
        "utilization_pct": 97.1,
        "account_yield_pct": 0.753,
        "meets_target": true
      }
    },
    {
      "account": "Account #3",
      "pick": {
        "symbol": "NVDA",
        "preferred": true,
        "company_name": "NVIDIA Corporation",
        "price": 197.66,
        "expiration": "2026-07-02",
        "dte": 8,
        "strike": 190.0,
        "bid": 1.67,
        "premium": 167.0,
        "pct_of_collateral": 0.879,
        "delta": -0.239,
        "open_interest": 9852,
        "collateral": 19000.0,
        "contracts": 3,
        "total_premium": 501.0,
        "utilization_pct": 95.6,
        "account_yield_pct": 0.84,
        "meets_target": true
      }
    },
    {
      "account": "Account #4",
      "pick": {
        "symbol": "ORCL",
        "preferred": true,
        "company_name": "Oracle Corporation",
        "price": 156.15,
        "expiration": "2026-06-26",
        "dte": 2,
        "strike": 150.0,
        "bid": 1.1,
        "premium": 110.0,
        "pct_of_collateral": 0.733,
        "delta": -0.224,
        "open_interest": 2697,
        "collateral": 15000.0,
        "contracts": 9,
        "total_premium": 990.0,
        "utilization_pct": 98.2,
        "account_yield_pct": 0.72,
        "meets_target": true
      }
    },
    {
      "account": "Account #6",
      "pick": {
        "symbol": "DAL",
        "preferred": true,
        "company_name": "Delta Air Lines, Inc.",
        "price": 90.04,
        "expiration": "2026-07-02",
        "dte": 8,
        "strike": 86.0,
        "bid": 0.69,
        "premium": 69.0,
        "pct_of_collateral": 0.802,
        "delta": -0.222,
        "open_interest": 27,
        "collateral": 8600.0,
        "contracts": 5,
        "total_premium": 345.0,
        "utilization_pct": 90.7,
        "account_yield_pct": 0.728,
        "meets_target": true
      }
    }
  ],
  "top_picks": [
    {
      "symbol": "PFE",
      "sector": "Healthcare",
      "thesis": "Pharma value; high dividend, low P/E",
      "available": true,
      "price": 24.02,
      "strike": 23.0,
      "expiration": "2026-07-31",
      "dte": 37,
      "bid": 0.28,
      "premium": 28.0,
      "delta": 0.304,
      "open_interest": 726,
      "collateral": 2300.0,
      "buyin": 22.72,
      "discount_pct": 5.39,
      "yield_pct": 1.217,
      "annualized_pct": 12.01
    },
    {
      "symbol": "BAC",
      "sector": "Financials",
      "thesis": "Quality diversified bank; rate beneficiary",
      "available": true,
      "price": 57.55,
      "strike": 55.0,
      "expiration": "2026-07-31",
      "dte": 37,
      "bid": 0.79,
      "premium": 79.0,
      "delta": 0.271,
      "open_interest": 101,
      "collateral": 5500.0,
      "buyin": 54.21,
      "discount_pct": 5.8,
      "yield_pct": 1.436,
      "annualized_pct": 14.17
    },
    {
      "symbol": "GM",
      "sector": "Autos",
      "thesis": "Deep value; very low P/E, big buybacks",
      "available": true,
      "price": 79.84,
      "strike": 75.0,
      "expiration": "2026-07-31",
      "dte": 37,
      "bid": 1.8,
      "premium": 180.0,
      "delta": 0.294,
      "open_interest": 27,
      "collateral": 7500.0,
      "buyin": 73.2,
      "discount_pct": 8.32,
      "yield_pct": 2.4,
      "annualized_pct": 23.68
    },
    {
      "symbol": "KMI",
      "sector": "Energy",
      "thesis": "Pipeline fee cash flows; steady income",
      "available": true,
      "price": 32.42,
      "strike": 31.0,
      "expiration": "2026-07-31",
      "dte": 37,
      "bid": 0.36,
      "premium": 36.0,
      "delta": 0.291,
      "open_interest": 14,
      "collateral": 3100.0,
      "buyin": 30.64,
      "discount_pct": 5.51,
      "yield_pct": 1.161,
      "annualized_pct": 11.46
    },
    {
      "symbol": "NU",
      "sector": "Fintech",
      "thesis": "LatAm digital bank; profitable growth",
      "available": false
    }
  ],
  "losers": [
    {
      "symbol": "MARA",
      "price": 13.66,
      "change_pct": -7.07,
      "company_name": "MARA Holdings, Inc.",
      "pe": null,
      "week52_high": 23.45,
      "week52_low": 6.66,
      "pct_below_high": 41.7,
      "preferred": false
    },
    {
      "symbol": "HOOD",
      "price": 97.02,
      "change_pct": -6.03,
      "company_name": "Robinhood Markets, Inc.",
      "pe": 46.97,
      "week52_high": 153.86,
      "week52_low": 63.515,
      "pct_below_high": 36.9,
      "preferred": false
    },
    {
      "symbol": "ORCL",
      "price": 156.15,
      "change_pct": -5.46,
      "company_name": "Oracle Corporation",
      "pe": 26.77,
      "week52_high": 345.72,
      "week52_low": 134.57,
      "pct_below_high": 54.8,
      "preferred": true
    },
    {
      "symbol": "QCOM",
      "price": 195.39,
      "change_pct": -4.28,
      "company_name": "QUALCOMM Incorporated",
      "pe": 21.08,
      "week52_high": 259.92,
      "week52_low": 121.99,
      "pct_below_high": 24.8,
      "preferred": false
    },
    {
      "symbol": "PLTR",
      "price": 112.78,
      "change_pct": -3.36,
      "company_name": "Palantir Technologies Inc.",
      "pe": 126.37,
      "week52_high": 207.52,
      "week52_low": 112.3,
      "pct_below_high": 45.7,
      "preferred": false
    },
    {
      "symbol": "PFE",
      "price": 24.02,
      "change_pct": -2.85,
      "company_name": "Pfizer Inc.",
      "pe": 18.31,
      "week52_high": 28.75,
      "week52_low": 23.11,
      "pct_below_high": 16.5,
      "preferred": false
    },
    {
      "symbol": "CVX",
      "price": 171.28,
      "change_pct": -2.67,
      "company_name": "Chevron Corporation",
      "pe": 29.89,
      "week52_high": 214.71,
      "week52_low": 142.4,
      "pct_below_high": 20.2,
      "preferred": false
    },
    {
      "symbol": "VZ",
      "price": 45.48,
      "change_pct": -2.66,
      "company_name": "Verizon Communications Inc.",
      "pe": 11.11,
      "week52_high": 51.68,
      "week52_low": 38.39,
      "pct_below_high": 12.0,
      "preferred": false
    },
    {
      "symbol": "XOM",
      "price": 136.48,
      "change_pct": -2.33,
      "company_name": "Exxon Mobil Corporation",
      "pe": 22.92,
      "week52_high": 176.41,
      "week52_low": 105.53,
      "pct_below_high": 22.6,
      "preferred": false
    },
    {
      "symbol": "NIO",
      "price": 4.98,
      "change_pct": -2.16,
      "company_name": "NIO Inc.",
      "pe": null,
      "week52_high": 8.02,
      "week52_low": 3.38,
      "pct_below_high": 37.9,
      "preferred": false
    }
  ],
  "params": {
    "max_underlying_price": 300.0,
    "dte_window": [
      21,
      45
    ],
    "yield_band_30d_pct": [
      0.7,
      1.0
    ],
    "max_abs_delta": 0.35,
    "min_open_interest": 50,
    "top_n": 20,
    "sorted_by": "premium"
  },
  "universe_size": 134,
  "scanned_under_price": 56,
  "total_qualifying": 90,
  "result_count": 20,
  "results": [
    {
      "symbol": "AAPL",
      "option_symbol": "AAPL260731P00275000",
      "price": 296.46,
      "expiration": "2026-07-31",
      "dte": 37,
      "strike": 275.0,
      "bid": 2.77,
      "delta": -0.185,
      "open_interest": 184,
      "collateral": 27500.0,
      "premium": 277.0,
      "yield_30d_pct": 0.817,
      "annualized_pct": 9.94,
      "preferred": false,
      "company_name": "Apple Inc.",
      "pe": 35.82,
      "week52_low": 199.26,
      "week52_high": 317.4,
      "weeklies": [
        {
          "expiration": "2026-06-26",
          "dte": 2,
          "puts": []
        },
        {
          "expiration": "2026-07-02",
          "dte": 8,
          "puts": [
            {
              "strike": 292.5,
              "bid": 2.68,
              "premium": 268.0,
              "pct_of_collateral": 0.916,
              "delta": -0.349,
              "open_interest": 2447,
              "recommended": true
            }
          ]
        },
        {
          "expiration": "2026-07-10",
          "dte": 16,
          "puts": [
            {
              "strike": 285.0,
              "bid": 2.0,
              "premium": 200.0,
              "pct_of_collateral": 0.702,
              "delta": -0.217,
              "open_interest": 889,
              "recommended": true
            },
            {
              "strike": 287.5,
              "bid": 2.45,
              "premium": 245.0,
              "pct_of_collateral": 0.852,
              "delta": -0.263,
              "open_interest": 80,
              "recommended": false
            }
          ]
        }
      ]
    },
    {
      "symbol": "BA",
      "option_symbol": "BA260731P00200000",
      "price": 221.29,
      "expiration": "2026-07-31",
      "dte": 37,
      "strike": 200.0,
      "bid": 2.27,
      "delta": -0.182,
      "open_interest": 60,
      "collateral": 20000.0,
      "premium": 227.0,
      "yield_30d_pct": 0.92,
      "annualized_pct": 11.2,
      "preferred": false,
      "company_name": "The Boeing Company",
      "pe": 86.78,
      "week52_low": 176.77,
      "week52_high": 254.35,
      "weeklies": [
        {
          "expiration": "2026-06-26",
          "dte": 2,
          "puts": [
            {
              "strike": 220.0,
              "bid": 2.0,
              "premium": 200.0,
              "pct_of_collateral": 0.909,
              "delta": -0.413,
              "open_interest": 2174,
              "recommended": true
            }
          ]
        },
        {
          "expiration": "2026-07-02",
          "dte": 8,
          "puts": [
            {
              "strike": 215.0,
              "bid": 1.9,
              "premium": 190.0,
              "pct_of_collateral": 0.884,
              "delta": -0.276,
              "open_interest": 1045,
              "recommended": true
            }
          ]
        },
        {
          "expiration": "2026-07-10",
          "dte": 16,
          "puts": [
            {
              "strike": 207.5,
              "bid": 1.46,
              "premium": 146.0,
              "pct_of_collateral": 0.704,
              "delta": -0.178,
              "open_interest": 15,
              "recommended": true
            },
            {
              "strike": 210.0,
              "bid": 1.97,
              "premium": 197.0,
              "pct_of_collateral": 0.938,
              "delta": -0.221,
              "open_interest": 294,
              "recommended": false
            }
          ]
        }
      ]
    },
    {
      "symbol": "AMZN",
      "option_symbol": "AMZN260724P00220000",
      "price": 239.26,
      "expiration": "2026-07-24",
      "dte": 30,
      "strike": 220.0,
      "bid": 2.2,
      "delta": -0.173,
      "open_interest": 952,
      "collateral": 22000.0,
      "premium": 220.0,
      "yield_30d_pct": 1.0,
      "annualized_pct": 12.17,
      "preferred": true,
      "company_name": "Amazon.com, Inc.",
      "pe": 32.25,
      "week52_low": 196.0,
      "week52_high": 278.56,
      "weeklies": [
        {
          "expiration": "2026-06-26",
          "dte": 2,
          "puts": [
            {
              "strike": 237.5,
              "bid": 2.05,
              "premium": 205.0,
              "pct_of_collateral": 0.863,
              "delta": -0.393,
              "open_interest": 2849,
              "recommended": true
            }
          ]
        },
        {
          "expiration": "2026-07-02",
          "dte": 8,
          "puts": [
            {
              "strike": 232.5,
              "bid": 2.1,
              "premium": 210.0,
              "pct_of_collateral": 0.903,
              "delta": -0.275,
              "open_interest": 412,
              "recommended": true
            }
          ]
        },
        {
          "expiration": "2026-07-10",
          "dte": 16,
          "puts": [
            {
              "strike": 225.0,
              "bid": 1.66,
              "premium": 166.0,
              "pct_of_collateral": 0.738,
              "delta": -0.177,
              "open_interest": 895,
              "recommended": true
            },
            {
              "strike": 227.5,
              "bid": 2.13,
              "premium": 213.0,
              "pct_of_collateral": 0.936,
              "delta": -0.218,
              "open_interest": 46,
              "recommended": false
            }
          ]
        }
      ]
    },
    {
      "symbol": "NVDA",
      "option_symbol": "NVDA260731P00175000",
      "price": 197.66,
      "expiration": "2026-07-31",
      "dte": 37,
      "strike": 175.0,
      "bid": 2.02,
      "delta": -0.15,
      "open_interest": 1191,
      "collateral": 17500.0,
      "premium": 202.0,
      "yield_30d_pct": 0.936,
      "annualized_pct": 11.39,
      "preferred": true,
      "company_name": "NVIDIA Corporation",
      "pe": 30.39,
      "week52_low": 149.26,
      "week52_high": 236.54,
      "weeklies": [
        {
          "expiration": "2026-06-26",
          "dte": 2,
          "puts": [
            {
              "strike": 195.0,
              "bid": 1.62,
              "premium": 162.0,
              "pct_of_collateral": 0.831,
              "delta": -0.342,
              "open_interest": 25512,
              "recommended": true
            }
          ]
        },
        {
          "expiration": "2026-07-02",
          "dte": 8,
          "puts": [
            {
              "strike": 190.0,
              "bid": 1.67,
              "premium": 167.0,
              "pct_of_collateral": 0.879,
              "delta": -0.239,
              "open_interest": 9852,
              "recommended": true
            }
          ]
        },
        {
          "expiration": "2026-07-10",
          "dte": 16,
          "puts": [
            {
              "strike": 185.0,
              "bid": 1.73,
              "premium": 173.0,
              "pct_of_collateral": 0.935,
              "delta": -0.191,
              "open_interest": 3431,
              "recommended": true
            }
          ]
        }
      ]
    },
    {
      "symbol": "CVX",
      "option_symbol": "CVX260731P00160000",
      "price": 171.28,
      "expiration": "2026-07-31",
      "dte": 37,
      "strike": 160.0,
      "bid": 1.52,
      "delta": -0.194,
      "open_interest": 116,
      "collateral": 16000.0,
      "premium": 152.0,
      "yield_30d_pct": 0.77,
      "annualized_pct": 9.37,
      "preferred": false,
      "company_name": "Chevron Corporation",
      "pe": 29.89,
      "week52_low": 142.4,
      "week52_high": 214.71,
      "weeklies": [
        {
          "expiration": "2026-06-26",
          "dte": 2,
          "puts": []
        },
        {
          "expiration": "2026-07-02",
          "dte": 8,
          "puts": []
        },
        {
          "expiration": "2026-07-10",
          "dte": 16,
          "puts": [
            {
              "strike": 165.0,
              "bid": 1.2,
              "premium": 120.0,
              "pct_of_collateral": 0.727,
              "delta": -0.227,
              "open_interest": 285,
              "recommended": true
            }
          ]
        }
      ]
    },
    {
      "symbol": "ORCL",
      "option_symbol": "ORCL260731P00125000",
      "price": 156.15,
      "expiration": "2026-07-31",
      "dte": 37,
      "strike": 125.0,
      "bid": 1.43,
      "delta": -0.105,
      "open_interest": 745,
      "collateral": 12500.0,
      "premium": 143.0,
      "yield_30d_pct": 0.928,
      "annualized_pct": 11.29,
      "preferred": true,
      "company_name": "Oracle Corporation",
      "pe": 26.78,
      "week52_low": 134.57,
      "week52_high": 345.72,
      "weeklies": [
        {
          "expiration": "2026-06-26",
          "dte": 2,
          "puts": [
            {
              "strike": 150.0,
              "bid": 1.1,
              "premium": 110.0,
              "pct_of_collateral": 0.733,
              "delta": -0.224,
              "open_interest": 2697,
              "recommended": true
            }
          ]
        },
        {
          "expiration": "2026-07-02",
          "dte": 8,
          "puts": []
        },
        {
          "expiration": "2026-07-10",
          "dte": 16,
          "puts": [
            {
              "strike": 135.0,
              "bid": 1.11,
              "premium": 111.0,
              "pct_of_collateral": 0.822,
              "delta": -0.118,
              "open_interest": 297,
              "recommended": true
            }
          ]
        }
      ]
    },
    {
      "symbol": "WMT",
      "option_symbol": "WMT260731P00114000",
      "price": 119.08,
      "expiration": "2026-07-31",
      "dte": 37,
      "strike": 114.0,
      "bid": 1.34,
      "delta": -0.268,
      "open_interest": 87,
      "collateral": 11400.0,
      "premium": 134.0,
      "yield_30d_pct": 0.953,
      "annualized_pct": 11.6,
      "preferred": false,
      "company_name": "Walmart Inc.",
      "pe": 41.98,
      "week52_low": 94.23,
      "week52_high": 135.16,
      "weeklies": [
        {
          "expiration": "2026-06-26",
          "dte": 2,
          "puts": [
            {
              "strike": 119.0,
              "bid": 0.99,
              "premium": 99.0,
              "pct_of_collateral": 0.832,
              "delta": -0.479,
              "open_interest": 1276,
              "recommended": true
            }
          ]
        },
        {
          "expiration": "2026-07-02",
          "dte": 8,
          "puts": [
            {
              "strike": 117.0,
              "bid": 0.88,
              "premium": 88.0,
              "pct_of_collateral": 0.752,
              "delta": -0.309,
              "open_interest": 287,
              "recommended": true
            }
          ]
        },
        {
          "expiration": "2026-07-10",
          "dte": 16,
          "puts": [
            {
              "strike": 115.0,
              "bid": 0.82,
              "premium": 82.0,
              "pct_of_collateral": 0.713,
              "delta": -0.236,
              "open_interest": 643,
              "recommended": true
            },
            {
              "strike": 116.0,
              "bid": 1.08,
              "premium": 108.0,
              "pct_of_collateral": 0.931,
              "delta": -0.288,
              "open_interest": 118,
              "recommended": false
            }
          ]
        }
      ]
    },
    {
      "symbol": "TGT",
      "option_symbol": "TGT260731P00127000",
      "price": 139.09,
      "expiration": "2026-07-31",
      "dte": 37,
      "strike": 127.0,
      "bid": 1.22,
      "delta": -0.171,
      "open_interest": 160,
      "collateral": 12700.0,
      "premium": 122.0,
      "yield_30d_pct": 0.779,
      "annualized_pct": 9.48,
      "preferred": false,
      "company_name": "Target Corporation",
      "pe": 18.43,
      "week52_low": 83.44,
      "week52_high": 139.4,
      "weeklies": [
        {
          "expiration": "2026-06-26",
          "dte": 2,
          "puts": [
            {
              "strike": 138.0,
              "bid": 1.03,
              "premium": 103.0,
              "pct_of_collateral": 0.746,
              "delta": -0.384,
              "open_interest": 109,
              "recommended": true
            },
            {
              "strike": 139.0,
              "bid": 1.38,
              "premium": 138.0,
              "pct_of_collateral": 0.993,
              "delta": -0.483,
              "open_interest": 30,
              "recommended": false
            }
          ]
        },
        {
          "expiration": "2026-07-02",
          "dte": 8,
          "puts": [
            {
              "strike": 135.0,
              "bid": 1.01,
              "premium": 101.0,
              "pct_of_collateral": 0.748,
              "delta": -0.256,
              "open_interest": 349,
              "recommended": true
            },
            {
              "strike": 136.0,
              "bid": 1.28,
              "premium": 128.0,
              "pct_of_collateral": 0.941,
              "delta": -0.305,
              "open_interest": 72,
              "recommended": false
            }
          ]
        },
        {
          "expiration": "2026-07-10",
          "dte": 16,
          "puts": [
            {
              "strike": 132.0,
              "bid": 0.94,
              "premium": 94.0,
              "pct_of_collateral": 0.712,
              "delta": -0.202,
              "open_interest": 59,
              "recommended": true
            },
            {
              "strike": 133.0,
              "bid": 1.15,
              "premium": 115.0,
              "pct_of_collateral": 0.865,
              "delta": -0.233,
              "open_interest": 30,
              "recommended": false
            }
          ]
        }
      ]
    },
    {
      "symbol": "QCOM",
      "option_symbol": "QCOM260724P00145000",
      "price": 195.39,
      "expiration": "2026-07-24",
      "dte": 30,
      "strike": 145.0,
      "bid": 1.14,
      "delta": -0.076,
      "open_interest": 54,
      "collateral": 14500.0,
      "premium": 114.0,
      "yield_30d_pct": 0.786,
      "annualized_pct": 9.57,
      "preferred": false,
      "company_name": "QUALCOMM Incorporated",
      "pe": 21.09,
      "week52_low": 121.99,
      "week52_high": 259.92,
      "weeklies": [
        {
          "expiration": "2026-06-26",
          "dte": 2,
          "puts": [
            {
              "strike": 170.0,
              "bid": 1.27,
              "premium": 127.0,
              "pct_of_collateral": 0.747,
              "delta": -0.114,
              "open_interest": 1911,
              "recommended": true
            },
            {
              "strike": 172.5,
              "bid": 1.59,
              "premium": 159.0,
              "pct_of_collateral": 0.922,
              "delta": -0.138,
              "open_interest": 325,
              "recommended": false
            }
          ]
        },
        {
          "expiration": "2026-07-02",
          "dte": 8,
          "puts": [
            {
              "strike": 165.0,
              "bid": 1.48,
              "premium": 148.0,
              "pct_of_collateral": 0.897,
              "delta": -0.112,
              "open_interest": 414,
              "recommended": true
            }
          ]
        },
        {
          "expiration": "2026-07-10",
          "dte": 16,
          "puts": [
            {
              "strike": 155.0,
              "bid": 1.34,
              "premium": 134.0,
              "pct_of_collateral": 0.865,
              "delta": -0.084,
              "open_interest": 318,
              "recommended": true
            }
          ]
        }
      ]
    },
    {
      "symbol": "MMM",
      "option_symbol": "MMM260717P00155000",
      "price": 167.65,
      "expiration": "2026-07-17",
      "dte": 23,
      "strike": 155.0,
      "bid": 1.07,
      "delta": -0.156,
      "open_interest": 1995,
      "collateral": 15500.0,
      "premium": 107.0,
      "yield_30d_pct": 0.9,
      "annualized_pct": 10.96,
      "preferred": false,
      "company_name": "3M Company",
      "pe": 32.02,
      "week52_low": 139.34,
      "week52_high": 177.41,
      "weeklies": [
        {
          "expiration": "2026-06-26",
          "dte": 2,
          "puts": [
            {
              "strike": 167.5,
              "bid": 1.4,
              "premium": 140.0,
              "pct_of_collateral": 0.836,
              "delta": -0.477,
              "open_interest": 1,
              "recommended": true
            }
          ]
        },
        {
          "expiration": "2026-07-02",
          "dte": 8,
          "puts": [
            {
              "strike": 165.0,
              "bid": 1.6,
              "premium": 160.0,
              "pct_of_collateral": 0.97,
              "delta": -0.344,
              "open_interest": 121,
              "recommended": true
            }
          ]
        },
        {
          "expiration": "2026-07-10",
          "dte": 16,
          "puts": [
            {
              "strike": 162.5,
              "bid": 1.56,
              "premium": 156.0,
              "pct_of_collateral": 0.96,
              "delta": -0.281,
              "open_interest": 1,
              "recommended": true
            }
          ]
        }
      ]
    },
    {
      "symbol": "ABNB",
      "option_symbol": "ABNB260724P00132000",
      "price": 146.38,
      "expiration": "2026-07-24",
      "dte": 30,
      "strike": 132.0,
      "bid": 1.04,
      "delta": -0.156,
      "open_interest": 116,
      "collateral": 13200.0,
      "premium": 104.0,
      "yield_30d_pct": 0.788,
      "annualized_pct": 9.59,
      "preferred": false,
      "company_name": "Airbnb, Inc.",
      "pe": 35.93,
      "week52_low": 110.81,
      "week52_high": 147.27,
      "weeklies": [
        {
          "expiration": "2026-06-26",
          "dte": 2,
          "puts": [
            {
              "strike": 145.0,
              "bid": 1.11,
              "premium": 111.0,
              "pct_of_collateral": 0.766,
              "delta": -0.382,
              "open_interest": 198,
              "recommended": true
            }
          ]
        },
        {
          "expiration": "2026-07-02",
          "dte": 8,
          "puts": [
            {
              "strike": 141.0,
              "bid": 1.02,
              "premium": 102.0,
              "pct_of_collateral": 0.723,
              "delta": -0.246,
              "open_interest": 24,
              "recommended": true
            },
            {
              "strike": 142.0,
              "bid": 1.23,
              "premium": 123.0,
              "pct_of_collateral": 0.866,
              "delta": -0.285,
              "open_interest": 3,
              "recommended": false
            }
          ]
        },
        {
          "expiration": "2026-07-10",
          "dte": 16,
          "puts": [
            {
              "strike": 137.0,
              "bid": 1.03,
              "premium": 103.0,
              "pct_of_collateral": 0.752,
              "delta": -0.189,
              "open_interest": 32,
              "recommended": true
            },
            {
              "strike": 138.0,
              "bid": 1.1,
              "premium": 110.0,
              "pct_of_collateral": 0.797,
              "delta": -0.212,
              "open_interest": 3,
              "recommended": false
            }
          ]
        }
      ]
    },
    {
      "symbol": "MRK",
      "option_symbol": "MRK260731P00113000",
      "price": 120.94,
      "expiration": "2026-07-31",
      "dte": 37,
      "strike": 113.0,
      "bid": 1.04,
      "delta": -0.206,
      "open_interest": 74,
      "collateral": 11300.0,
      "premium": 104.0,
      "yield_30d_pct": 0.746,
      "annualized_pct": 9.08,
      "preferred": false,
      "company_name": "Merck & Co., Inc.",
      "pe": 33.84,
      "week52_low": 76.66,
      "week52_high": 125.14,
      "weeklies": [
        {
          "expiration": "2026-06-26",
          "dte": 2,
          "puts": []
        },
        {
          "expiration": "2026-07-02",
          "dte": 8,
          "puts": [
            {
              "strike": 119.0,
              "bid": 1.02,
              "premium": 102.0,
              "pct_of_collateral": 0.857,
              "delta": -0.336,
              "open_interest": 96,
              "recommended": true
            }
          ]
        },
        {
          "expiration": "2026-07-10",
          "dte": 16,
          "puts": [
            {
              "strike": 117.0,
              "bid": 1.04,
              "premium": 104.0,
              "pct_of_collateral": 0.889,
              "delta": -0.266,
              "open_interest": 80,
              "recommended": true
            }
          ]
        }
      ]
    },
    {
      "symbol": "SBUX",
      "option_symbol": "SBUX260731P00092000",
      "price": 100.98,
      "expiration": "2026-07-31",
      "dte": 37,
      "strike": 92.0,
      "bid": 0.98,
      "delta": -0.191,
      "open_interest": 87,
      "collateral": 9200.0,
      "premium": 98.0,
      "yield_30d_pct": 0.864,
      "annualized_pct": 10.51,
      "preferred": false,
      "company_name": "Starbucks Corporation",
      "pe": 78.98,
      "week52_low": 77.99,
      "week52_high": 108.88,
      "weeklies": [
        {
          "expiration": "2026-06-26",
          "dte": 2,
          "puts": []
        },
        {
          "expiration": "2026-07-02",
          "dte": 8,
          "puts": [
            {
              "strike": 99.0,
              "bid": 0.89,
              "premium": 89.0,
              "pct_of_collateral": 0.899,
              "delta": -0.314,
              "open_interest": 97,
              "recommended": true
            }
          ]
        },
        {
          "expiration": "2026-07-10",
          "dte": 16,
          "puts": [
            {
              "strike": 98.0,
              "bid": 0.96,
              "premium": 96.0,
              "pct_of_collateral": 0.98,
              "delta": -0.281,
              "open_interest": 205,
              "recommended": true
            }
          ]
        }
      ]
    },
    {
      "symbol": "C",
      "option_symbol": "C260724P00131000",
      "price": 144.77,
      "expiration": "2026-07-24",
      "dte": 30,
      "strike": 131.0,
      "bid": 0.93,
      "delta": -0.148,
      "open_interest": 50,
      "collateral": 13100.0,
      "premium": 93.0,
      "yield_30d_pct": 0.71,
      "annualized_pct": 8.64,
      "preferred": false,
      "company_name": "Citigroup Inc.",
      "pe": 17.8,
      "week52_low": 81.08,
      "week52_high": 147.96,
      "weeklies": [
        {
          "expiration": "2026-06-26",
          "dte": 2,
          "puts": [
            {
              "strike": 144.0,
              "bid": 1.19,
              "premium": 119.0,
              "pct_of_collateral": 0.826,
              "delta": -0.417,
              "open_interest": 5303,
              "recommended": true
            }
          ]
        },
        {
          "expiration": "2026-07-02",
          "dte": 8,
          "puts": [
            {
              "strike": 141.0,
              "bid": 1.12,
              "premium": 112.0,
              "pct_of_collateral": 0.794,
              "delta": -0.277,
              "open_interest": 118,
              "recommended": true
            },
            {
              "strike": 142.0,
              "bid": 1.39,
              "premium": 139.0,
              "pct_of_collateral": 0.979,
              "delta": -0.326,
              "open_interest": 873,
              "recommended": false
            }
          ]
        },
        {
          "expiration": "2026-07-10",
          "dte": 16,
          "puts": [
            {
              "strike": 138.0,
              "bid": 1.11,
              "premium": 111.0,
              "pct_of_collateral": 0.804,
              "delta": -0.213,
              "open_interest": 49,
              "recommended": true
            },
            {
              "strike": 139.0,
              "bid": 1.31,
              "premium": 131.0,
              "pct_of_collateral": 0.942,
              "delta": -0.244,
              "open_interest": 94,
              "recommended": false
            }
          ]
        }
      ]
    },
    {
      "symbol": "INTC",
      "option_symbol": "INTC260731P00080000",
      "price": 130.32,
      "expiration": "2026-07-31",
      "dte": 37,
      "strike": 80.0,
      "bid": 0.87,
      "delta": -0.053,
      "open_interest": 398,
      "collateral": 8000.0,
      "premium": 87.0,
      "yield_30d_pct": 0.882,
      "annualized_pct": 10.73,
      "preferred": true,
      "company_name": "Intel Corporation",
      "pe": null,
      "week52_low": 18.97,
      "week52_high": 141.45,
      "weeklies": [
        {
          "expiration": "2026-06-26",
          "dte": 2,
          "puts": [
            {
              "strike": 119.0,
              "bid": 0.98,
              "premium": 98.0,
              "pct_of_collateral": 0.824,
              "delta": -0.154,
              "open_interest": 1790,
              "recommended": true
            },
            {
              "strike": 120.0,
              "bid": 1.12,
              "premium": 112.0,
              "pct_of_collateral": 0.933,
              "delta": -0.175,
              "open_interest": 10764,
              "recommended": false
            }
          ]
        },
        {
          "expiration": "2026-07-02",
          "dte": 8,
          "puts": [
            {
              "strike": 107.0,
              "bid": 0.83,
              "premium": 83.0,
              "pct_of_collateral": 0.776,
              "delta": -0.089,
              "open_interest": 452,
              "recommended": true
            },
            {
              "strike": 108.0,
              "bid": 0.92,
              "premium": 92.0,
              "pct_of_collateral": 0.852,
              "delta": -0.097,
              "open_interest": 506,
              "recommended": false
            },
            {
              "strike": 109.0,
              "bid": 1.01,
              "premium": 101.0,
              "pct_of_collateral": 0.927,
              "delta": -0.106,
              "open_interest": 285,
              "recommended": false
            }
          ]
        },
        {
          "expiration": "2026-07-10",
          "dte": 16,
          "puts": [
            {
              "strike": 95.0,
              "bid": 0.68,
              "premium": 68.0,
              "pct_of_collateral": 0.716,
              "delta": -0.058,
              "open_interest": 1046,
              "recommended": true
            },
            {
              "strike": 96.0,
              "bid": 0.68,
              "premium": 68.0,
              "pct_of_collateral": 0.708,
              "delta": -0.062,
              "open_interest": 134,
              "recommended": false
            },
            {
              "strike": 97.0,
              "bid": 0.74,
              "premium": 74.0,
              "pct_of_collateral": 0.763,
              "delta": -0.067,
              "open_interest": 425,
              "recommended": false
            }
          ]
        }
      ]
    },
    {
      "symbol": "PLTR",
      "option_symbol": "PLTR260731P00090000",
      "price": 112.78,
      "expiration": "2026-07-31",
      "dte": 37,
      "strike": 90.0,
      "bid": 0.85,
      "delta": -0.09,
      "open_interest": 131,
      "collateral": 9000.0,
      "premium": 85.0,
      "yield_30d_pct": 0.766,
      "annualized_pct": 9.32,
      "preferred": false,
      "company_name": "Palantir Technologies Inc.",
      "pe": 126.38,
      "week52_low": 112.3,
      "week52_high": 207.52,
      "weeklies": [
        {
          "expiration": "2026-06-26",
          "dte": 2,
          "puts": [
            {
              "strike": 109.0,
              "bid": 0.82,
              "premium": 82.0,
              "pct_of_collateral": 0.752,
              "delta": -0.239,
              "open_interest": 814,
              "recommended": true
            },
            {
              "strike": 110.0,
              "bid": 1.07,
              "premium": 107.0,
              "pct_of_collateral": 0.973,
              "delta": -0.295,
              "open_interest": 4812,
              "recommended": false
            }
          ]
        },
        {
          "expiration": "2026-07-02",
          "dte": 8,
          "puts": [
            {
              "strike": 104.0,
              "bid": 0.83,
              "premium": 83.0,
              "pct_of_collateral": 0.798,
              "delta": -0.16,
              "open_interest": 46,
              "recommended": true
            },
            {
              "strike": 105.0,
              "bid": 0.97,
              "premium": 97.0,
              "pct_of_collateral": 0.924,
              "delta": -0.186,
              "open_interest": 630,
              "recommended": false
            }
          ]
        },
        {
          "expiration": "2026-07-10",
          "dte": 16,
          "puts": [
            {
              "strike": 100.0,
              "bid": 0.95,
              "premium": 95.0,
              "pct_of_collateral": 0.95,
              "delta": -0.136,
              "open_interest": 634,
              "recommended": true
            }
          ]
        }
      ]
    },
    {
      "symbol": "KO",
      "option_symbol": "KO260731P00078000",
      "price": 81.06,
      "expiration": "2026-07-31",
      "dte": 37,
      "strike": 78.0,
      "bid": 0.8,
      "delta": -0.262,
      "open_interest": 92,
      "collateral": 7800.0,
      "premium": 80.0,
      "yield_30d_pct": 0.832,
      "annualized_pct": 10.12,
      "preferred": false,
      "company_name": "The Coca-Cola Company",
      "pe": 25.39,
      "week52_low": 65.35,
      "week52_high": 84.04,
      "weeklies": [
        {
          "expiration": "2026-06-26",
          "dte": 2,
          "puts": []
        },
        {
          "expiration": "2026-07-02",
          "dte": 8,
          "puts": [
            {
              "strike": 81.0,
              "bid": 0.8,
              "premium": 80.0,
              "pct_of_collateral": 0.988,
              "delta": -0.473,
              "open_interest": 46,
              "recommended": true
            }
          ]
        },
        {
          "expiration": "2026-07-10",
          "dte": 16,
          "puts": [
            {
              "strike": 80.0,
              "bid": 0.69,
              "premium": 69.0,
              "pct_of_collateral": 0.862,
              "delta": -0.347,
              "open_interest": 144,
              "recommended": true
            }
          ]
        }
      ]
    },
    {
      "symbol": "NEE",
      "option_symbol": "NEE260724P00082000",
      "price": 86.68,
      "expiration": "2026-07-24",
      "dte": 30,
      "strike": 82.0,
      "bid": 0.73,
      "delta": -0.222,
      "open_interest": 77,
      "collateral": 8200.0,
      "premium": 73.0,
      "yield_30d_pct": 0.89,
      "annualized_pct": 10.83,
      "preferred": false,
      "company_name": "NextEra Energy, Inc.",
      "pe": 22.02,
      "week52_low": 67.2,
      "week52_high": 98.75,
      "weeklies": [
        {
          "expiration": "2026-06-26",
          "dte": 2,
          "puts": []
        },
        {
          "expiration": "2026-07-02",
          "dte": 8,
          "puts": [
            {
              "strike": 86.0,
              "bid": 0.85,
              "premium": 85.0,
              "pct_of_collateral": 0.988,
              "delta": -0.402,
              "open_interest": 45,
              "recommended": true
            }
          ]
        },
        {
          "expiration": "2026-07-10",
          "dte": 16,
          "puts": [
            {
              "strike": 84.0,
              "bid": 0.61,
              "premium": 61.0,
              "pct_of_collateral": 0.726,
              "delta": -0.25,
              "open_interest": 40,
              "recommended": true
            }
          ]
        }
      ]
    },
    {
      "symbol": "HOOD",
      "option_symbol": "HOOD260724P00075000",
      "price": 97.02,
      "expiration": "2026-07-24",
      "dte": 30,
      "strike": 75.0,
      "bid": 0.71,
      "delta": -0.094,
      "open_interest": 141,
      "collateral": 7500.0,
      "premium": 71.0,
      "yield_30d_pct": 0.947,
      "annualized_pct": 11.52,
      "preferred": false,
      "company_name": "Robinhood Markets, Inc.",
      "pe": 47.03,
      "week52_low": 63.515,
      "week52_high": 153.86,
      "weeklies": [
        {
          "expiration": "2026-06-26",
          "dte": 2,
          "puts": [
            {
              "strike": 91.0,
              "bid": 0.69,
              "premium": 69.0,
              "pct_of_collateral": 0.758,
              "delta": -0.182,
              "open_interest": 327,
              "recommended": true
            },
            {
              "strike": 92.0,
              "bid": 0.86,
              "premium": 86.0,
              "pct_of_collateral": 0.935,
              "delta": -0.221,
              "open_interest": 1489,
              "recommended": false
            }
          ]
        },
        {
          "expiration": "2026-07-02",
          "dte": 8,
          "puts": [
            {
              "strike": 84.0,
              "bid": 0.61,
              "premium": 61.0,
              "pct_of_collateral": 0.726,
              "delta": -0.11,
              "open_interest": 93,
              "recommended": true
            },
            {
              "strike": 85.0,
              "bid": 0.75,
              "premium": 75.0,
              "pct_of_collateral": 0.882,
              "delta": -0.126,
              "open_interest": 602,
              "recommended": false
            }
          ]
        },
        {
          "expiration": "2026-07-10",
          "dte": 16,
          "puts": [
            {
              "strike": 79.0,
              "bid": 0.61,
              "premium": 61.0,
              "pct_of_collateral": 0.772,
              "delta": -0.09,
              "open_interest": 75,
              "recommended": true
            },
            {
              "strike": 80.0,
              "bid": 0.7,
              "premium": 70.0,
              "pct_of_collateral": 0.875,
              "delta": -0.101,
              "open_interest": 811,
              "recommended": false
            },
            {
              "strike": 81.0,
              "bid": 0.81,
              "premium": 81.0,
              "pct_of_collateral": 1.0,
              "delta": -0.113,
              "open_interest": 100,
              "recommended": false
            }
          ]
        }
      ]
    },
    {
      "symbol": "NOW",
      "option_symbol": "NOW260731P00070000",
      "price": 93.88,
      "expiration": "2026-07-31",
      "dte": 37,
      "strike": 70.0,
      "bid": 0.7,
      "delta": -0.073,
      "open_interest": 164,
      "collateral": 7000.0,
      "premium": 70.0,
      "yield_30d_pct": 0.811,
      "annualized_pct": 9.86,
      "preferred": false,
      "company_name": "ServiceNow, Inc.",
      "pe": 55.74,
      "week52_low": 81.24,
      "week52_high": 211.478,
      "weeklies": [
        {
          "expiration": "2026-06-26",
          "dte": 2,
          "puts": [
            {
              "strike": 91.0,
              "bid": 0.75,
              "premium": 75.0,
              "pct_of_collateral": 0.824,
              "delta": -0.262,
              "open_interest": 2187,
              "recommended": true
            }
          ]
        },
        {
          "expiration": "2026-07-02",
          "dte": 8,
          "puts": [
            {
              "strike": 86.0,
              "bid": 0.65,
              "premium": 65.0,
              "pct_of_collateral": 0.756,
              "delta": -0.149,
              "open_interest": 34,
              "recommended": true
            },
            {
              "strike": 87.0,
              "bid": 0.8,
              "premium": 80.0,
              "pct_of_collateral": 0.92,
              "delta": -0.18,
              "open_interest": 94,
              "recommended": false
            }
          ]
        },
        {
          "expiration": "2026-07-10",
          "dte": 16,
          "puts": []
        }
      ]
    }
  ],
  "indices": []
}