{
  "generated_at": "2026-07-22T21:09:05",
  "data_source": "CBOE delayed (~15 min)",
  "account_picks": [
    {
      "account": "Account #1",
      "pick": {
        "symbol": "SMCI",
        "preferred": true,
        "company_name": "Super Micro Computer, Inc.",
        "price": 30.7,
        "expiration": "2026-07-31",
        "dte": 9,
        "strike": 25.0,
        "bid": 0.23,
        "premium": 23.0,
        "pct_of_collateral": 0.92,
        "delta": -0.1,
        "open_interest": 1935,
        "collateral": 2500.0,
        "contracts": 8,
        "total_premium": 184.0,
        "utilization_pct": 90.7,
        "account_yield_pct": 0.835,
        "meets_target": true
      }
    },
    {
      "account": "Account #3",
      "pick": {
        "symbol": "ORCL",
        "preferred": true,
        "company_name": "Oracle Corporation",
        "price": 126.6,
        "expiration": "2026-07-31",
        "dte": 9,
        "strike": 111.0,
        "bid": 0.9,
        "premium": 90.0,
        "pct_of_collateral": 0.811,
        "delta": -0.126,
        "open_interest": 340,
        "collateral": 11100.0,
        "contracts": 5,
        "total_premium": 450.0,
        "utilization_pct": 93.1,
        "account_yield_pct": 0.755,
        "meets_target": true
      }
    },
    {
      "account": "Account #4",
      "pick": {
        "symbol": "AMZN",
        "preferred": true,
        "company_name": "Amazon.com, Inc.",
        "price": 244.94,
        "expiration": "2026-07-31",
        "dte": 9,
        "strike": 220.0,
        "bid": 1.62,
        "premium": 162.0,
        "pct_of_collateral": 0.736,
        "delta": -0.132,
        "open_interest": 2664,
        "collateral": 22000.0,
        "contracts": 6,
        "total_premium": 972.0,
        "utilization_pct": 96.1,
        "account_yield_pct": 0.707,
        "meets_target": true
      }
    },
    {
      "account": "Account #6",
      "pick": {
        "symbol": "INTC",
        "preferred": true,
        "company_name": "Intel Corporation",
        "price": 103.4,
        "expiration": "2026-07-31",
        "dte": 9,
        "strike": 75.0,
        "bid": 0.62,
        "premium": 62.0,
        "pct_of_collateral": 0.827,
        "delta": -0.063,
        "open_interest": 2117,
        "collateral": 7500.0,
        "contracts": 6,
        "total_premium": 372.0,
        "utilization_pct": 94.9,
        "account_yield_pct": 0.784,
        "meets_target": true
      }
    }
  ],
  "top_picks": [
    {
      "symbol": "PFE",
      "sector": "Healthcare",
      "thesis": "Pharma value; high dividend, low P/E",
      "available": true,
      "price": 24.9,
      "strike": 23.5,
      "expiration": "2026-08-28",
      "dte": 37,
      "bid": 0.32,
      "premium": 32.0,
      "delta": 0.288,
      "open_interest": 116,
      "collateral": 2350.0,
      "buyin": 23.18,
      "discount_pct": 6.91,
      "yield_pct": 1.362,
      "annualized_pct": 13.43
    },
    {
      "symbol": "BAC",
      "sector": "Financials",
      "thesis": "Quality diversified bank; rate beneficiary",
      "available": true,
      "price": 61.62,
      "strike": 60.0,
      "expiration": "2026-08-21",
      "dte": 30,
      "bid": 0.84,
      "premium": 84.0,
      "delta": 0.317,
      "open_interest": 8687,
      "collateral": 6000.0,
      "buyin": 59.16,
      "discount_pct": 3.99,
      "yield_pct": 1.4,
      "annualized_pct": 17.03
    },
    {
      "symbol": "GM",
      "sector": "Autos",
      "thesis": "Deep value; very low P/E, big buybacks",
      "available": true,
      "price": 82.13,
      "strike": 78.0,
      "expiration": "2026-08-28",
      "dte": 37,
      "bid": 1.49,
      "premium": 149.0,
      "delta": 0.292,
      "open_interest": 30,
      "collateral": 7800.0,
      "buyin": 76.51,
      "discount_pct": 6.84,
      "yield_pct": 1.91,
      "annualized_pct": 18.84
    },
    {
      "symbol": "KMI",
      "sector": "Energy",
      "thesis": "Pipeline fee cash flows; steady income",
      "available": true,
      "price": 32.51,
      "strike": 31.0,
      "expiration": "2026-08-28",
      "dte": 37,
      "bid": 0.45,
      "premium": 45.0,
      "delta": 0.298,
      "open_interest": 9,
      "collateral": 3100.0,
      "buyin": 30.55,
      "discount_pct": 6.03,
      "yield_pct": 1.452,
      "annualized_pct": 14.32
    },
    {
      "symbol": "NU",
      "sector": "Fintech",
      "thesis": "LatAm digital bank; profitable growth",
      "available": true,
      "price": 14.51,
      "strike": 13.5,
      "expiration": "2026-08-28",
      "dte": 37,
      "bid": 0.36,
      "premium": 36.0,
      "delta": 0.285,
      "open_interest": 8,
      "collateral": 1350.0,
      "buyin": 13.14,
      "discount_pct": 9.44,
      "yield_pct": 2.667,
      "annualized_pct": 26.31
    }
  ],
  "losers": [
    {
      "symbol": "PLTR",
      "price": 124.62,
      "change_pct": -6.1,
      "company_name": "Palantir Technologies Inc.",
      "pe": 139.97,
      "week52_high": 207.52,
      "week52_low": 106.37,
      "pct_below_high": 39.9,
      "preferred": false
    },
    {
      "symbol": "COIN",
      "price": 166.66,
      "change_pct": -5.53,
      "company_name": "Coinbase Global, Inc.",
      "pe": 60.85,
      "week52_high": 405.31,
      "week52_low": 139.18,
      "pct_below_high": 58.9,
      "preferred": false
    },
    {
      "symbol": "CRM",
      "price": 164.11,
      "change_pct": -4.15,
      "company_name": "Salesforce, Inc.",
      "pe": 18.91,
      "week52_high": 274.0,
      "week52_low": 146.32,
      "pct_below_high": 40.1,
      "preferred": false
    },
    {
      "symbol": "AAL",
      "price": 14.68,
      "change_pct": -3.95,
      "company_name": "American Airlines Group Inc.",
      "pe": 47.71,
      "week52_high": 18.79,
      "week52_low": 10.09,
      "pct_below_high": 21.9,
      "preferred": false
    },
    {
      "symbol": "SHOP",
      "price": 118.41,
      "change_pct": -3.75,
      "company_name": "Shopify Inc.",
      "pe": 116.1,
      "week52_high": 182.19,
      "week52_low": 94.0,
      "pct_below_high": 35.0,
      "preferred": false
    },
    {
      "symbol": "RIVN",
      "price": 17.18,
      "change_pct": -3.27,
      "company_name": "Rivian Automotive, Inc.",
      "pe": null,
      "week52_high": 22.69,
      "week52_low": 11.57,
      "pct_below_high": 24.3,
      "preferred": false
    },
    {
      "symbol": "SOFI",
      "price": 17.11,
      "change_pct": -3.23,
      "company_name": "SoFi Technologies, Inc.",
      "pe": 37.93,
      "week52_high": 32.73,
      "week52_low": 14.92,
      "pct_below_high": 47.7,
      "preferred": false
    },
    {
      "symbol": "ABNB",
      "price": 140.05,
      "change_pct": -2.81,
      "company_name": "Airbnb, Inc.",
      "pe": 34.58,
      "week52_high": 150.88,
      "week52_low": 110.81,
      "pct_below_high": 7.2,
      "preferred": false
    },
    {
      "symbol": "INTC",
      "price": 103.4,
      "change_pct": -2.68,
      "company_name": "Intel Corporation",
      "pe": null,
      "week52_high": 142.35,
      "week52_low": 18.97,
      "pct_below_high": 27.4,
      "preferred": true
    },
    {
      "symbol": "NIO",
      "price": 4.67,
      "change_pct": -2.51,
      "company_name": "NIO Inc.",
      "pe": null,
      "week52_high": 8.02,
      "week52_low": 4.37,
      "pct_below_high": 41.8,
      "preferred": false
    }
  ],
  "params": {
    "max_underlying_price": 300.0,
    "dte_window": [
      21,
      45
    ],
    "yield_band_30d_pct": [
      0.7,
      1.0
    ],
    "max_abs_delta": 0.35,
    "min_open_interest": 50,
    "top_n": 20,
    "sorted_by": "premium"
  },
  "universe_size": 134,
  "scanned_under_price": 58,
  "total_qualifying": 100,
  "result_count": 20,
  "results": [
    {
      "symbol": "AMZN",
      "option_symbol": "AMZN260828P00215000",
      "price": 244.94,
      "expiration": "2026-08-28",
      "dte": 37,
      "strike": 215.0,
      "bid": 2.55,
      "delta": -0.15,
      "open_interest": 205,
      "collateral": 21500.0,
      "premium": 255.0,
      "yield_30d_pct": 0.962,
      "annualized_pct": 11.7,
      "preferred": true,
      "company_name": "Amazon.com, Inc.",
      "pe": 29.25,
      "week52_low": 196.0,
      "week52_high": 278.56,
      "weeklies": [
        {
          "expiration": "2026-07-24",
          "dte": 2,
          "puts": [
            {
              "strike": 242.5,
              "bid": 1.88,
              "premium": 188.0,
              "pct_of_collateral": 0.775,
              "delta": -0.369,
              "open_interest": 3249,
              "recommended": true
            }
          ]
        },
        {
          "expiration": "2026-07-31",
          "dte": 9,
          "puts": [
            {
              "strike": 220.0,
              "bid": 1.62,
              "premium": 162.0,
              "pct_of_collateral": 0.736,
              "delta": -0.132,
              "open_interest": 2664,
              "recommended": true
            },
            {
              "strike": 222.5,
              "bid": 1.98,
              "premium": 198.0,
              "pct_of_collateral": 0.89,
              "delta": -0.155,
              "open_interest": 250,
              "recommended": false
            }
          ]
        },
        {
          "expiration": "2026-08-07",
          "dte": 16,
          "puts": [
            {
              "strike": 220.0,
              "bid": 2.08,
              "premium": 208.0,
              "pct_of_collateral": 0.945,
              "delta": -0.152,
              "open_interest": 1858,
              "recommended": true
            }
          ]
        }
      ]
    },
    {
      "symbol": "NVDA",
      "option_symbol": "NVDA260828P00180000",
      "price": 212.53,
      "expiration": "2026-08-28",
      "dte": 37,
      "strike": 180.0,
      "bid": 2.1,
      "delta": -0.125,
      "open_interest": 1213,
      "collateral": 18000.0,
      "premium": 210.0,
      "yield_30d_pct": 0.946,
      "annualized_pct": 11.51,
      "preferred": true,
      "company_name": "NVIDIA Corporation",
      "pe": 32.47,
      "week52_low": 164.07,
      "week52_high": 236.54,
      "weeklies": [
        {
          "expiration": "2026-07-24",
          "dte": 2,
          "puts": [
            {
              "strike": 210.0,
              "bid": 1.83,
              "premium": 183.0,
              "pct_of_collateral": 0.871,
              "delta": -0.374,
              "open_interest": 7558,
              "recommended": true
            }
          ]
        },
        {
          "expiration": "2026-07-31",
          "dte": 9,
          "puts": [
            {
              "strike": 202.5,
              "bid": 1.81,
              "premium": 181.0,
              "pct_of_collateral": 0.894,
              "delta": -0.225,
              "open_interest": 1137,
              "recommended": true
            }
          ]
        },
        {
          "expiration": "2026-08-07",
          "dte": 16,
          "puts": [
            {
              "strike": 195.0,
              "bid": 1.52,
              "premium": 152.0,
              "pct_of_collateral": 0.779,
              "delta": -0.158,
              "open_interest": 2763,
              "recommended": true
            },
            {
              "strike": 197.5,
              "bid": 1.91,
              "premium": 191.0,
              "pct_of_collateral": 0.967,
              "delta": -0.191,
              "open_interest": 502,
              "recommended": false
            }
          ]
        }
      ]
    },
    {
      "symbol": "ARM",
      "option_symbol": "ARM260821P00170000",
      "price": 282.27,
      "expiration": "2026-08-21",
      "dte": 30,
      "strike": 170.0,
      "bid": 1.6,
      "delta": -0.049,
      "open_interest": 6099,
      "collateral": 17000.0,
      "premium": 160.0,
      "yield_30d_pct": 0.941,
      "annualized_pct": 11.45,
      "preferred": false,
      "company_name": "Arm Holdings plc",
      "pe": 337.38,
      "week52_low": 100.02,
      "week52_high": 452.7,
      "weeklies": [
        {
          "expiration": "2026-07-24",
          "dte": 2,
          "puts": [
            {
              "strike": 255.0,
              "bid": 2.06,
              "premium": 206.0,
              "pct_of_collateral": 0.808,
              "delta": -0.142,
              "open_interest": 1132,
              "recommended": true
            },
            {
              "strike": 257.5,
              "bid": 2.16,
              "premium": 216.0,
              "pct_of_collateral": 0.839,
              "delta": -0.163,
              "open_interest": 177,
              "recommended": false
            }
          ]
        },
        {
          "expiration": "2026-07-31",
          "dte": 9,
          "puts": [
            {
              "strike": 200.0,
              "bid": 1.49,
              "premium": 149.0,
              "pct_of_collateral": 0.745,
              "delta": -0.056,
              "open_interest": 251,
              "recommended": true
            },
            {
              "strike": 202.5,
              "bid": 1.7,
              "premium": 170.0,
              "pct_of_collateral": 0.84,
              "delta": -0.062,
              "open_interest": 137,
              "recommended": false
            },
            {
              "strike": 205.0,
              "bid": 1.92,
              "premium": 192.0,
              "pct_of_collateral": 0.937,
              "delta": -0.068,
              "open_interest": 80,
              "recommended": false
            }
          ]
        },
        {
          "expiration": "2026-08-07",
          "dte": 16,
          "puts": [
            {
              "strike": 190.0,
              "bid": 1.77,
              "premium": 177.0,
              "pct_of_collateral": 0.932,
              "delta": -0.059,
              "open_interest": 16,
              "recommended": true
            }
          ]
        }
      ]
    },
    {
      "symbol": "XOM",
      "option_symbol": "XOM260828P00145000",
      "price": 154.4,
      "expiration": "2026-08-28",
      "dte": 37,
      "strike": 145.0,
      "bid": 1.57,
      "delta": -0.257,
      "open_interest": 163,
      "collateral": 14500.0,
      "premium": 157.0,
      "yield_30d_pct": 0.878,
      "annualized_pct": 10.68,
      "preferred": false,
      "company_name": "ExxonMobil Holdings Corporation",
      "pe": 25.96,
      "week52_low": 105.53,
      "week52_high": 176.41,
      "weeklies": [
        {
          "expiration": "2026-07-24",
          "dte": 2,
          "puts": []
        },
        {
          "expiration": "2026-07-31",
          "dte": 9,
          "puts": [
            {
              "strike": 149.0,
              "bid": 1.13,
              "premium": 113.0,
              "pct_of_collateral": 0.758,
              "delta": -0.243,
              "open_interest": 84,
              "recommended": true
            },
            {
              "strike": 150.0,
              "bid": 1.49,
              "premium": 149.0,
              "pct_of_collateral": 0.993,
              "delta": -0.283,
              "open_interest": 123,
              "recommended": false
            }
          ]
        },
        {
          "expiration": "2026-08-07",
          "dte": 16,
          "puts": [
            {
              "strike": 147.0,
              "bid": 1.19,
              "premium": 119.0,
              "pct_of_collateral": 0.81,
              "delta": -0.22,
              "open_interest": 26,
              "recommended": true
            },
            {
              "strike": 148.0,
              "bid": 1.46,
              "premium": 146.0,
              "pct_of_collateral": 0.986,
              "delta": -0.251,
              "open_interest": 32,
              "recommended": false
            }
          ]
        }
      ]
    },
    {
      "symbol": "BA",
      "option_symbol": "BA260821P00185000",
      "price": 208.36,
      "expiration": "2026-08-21",
      "dte": 30,
      "strike": 185.0,
      "bid": 1.53,
      "delta": -0.134,
      "open_interest": 3570,
      "collateral": 18500.0,
      "premium": 153.0,
      "yield_30d_pct": 0.827,
      "annualized_pct": 10.06,
      "preferred": false,
      "company_name": "The Boeing Company",
      "pe": 82.15,
      "week52_low": 176.77,
      "week52_high": 254.35,
      "weeklies": [
        {
          "expiration": "2026-07-24",
          "dte": 2,
          "puts": [
            {
              "strike": 207.5,
              "bid": 1.68,
              "premium": 168.0,
              "pct_of_collateral": 0.81,
              "delta": -0.415,
              "open_interest": 1635,
              "recommended": true
            }
          ]
        },
        {
          "expiration": "2026-07-31",
          "dte": 9,
          "puts": [
            {
              "strike": 195.0,
              "bid": 1.74,
              "premium": 174.0,
              "pct_of_collateral": 0.892,
              "delta": -0.191,
              "open_interest": 306,
              "recommended": true
            }
          ]
        },
        {
          "expiration": "2026-08-07",
          "dte": 16,
          "puts": [
            {
              "strike": 190.0,
              "bid": 1.5,
              "premium": 150.0,
              "pct_of_collateral": 0.789,
              "delta": -0.151,
              "open_interest": 93,
              "recommended": true
            },
            {
              "strike": 192.5,
              "bid": 1.7,
              "premium": 170.0,
              "pct_of_collateral": 0.883,
              "delta": -0.182,
              "open_interest": 26,
              "recommended": false
            },
            {
              "strike": 195.0,
              "bid": 1.91,
              "premium": 191.0,
              "pct_of_collateral": 0.979,
              "delta": -0.218,
              "open_interest": 135,
              "recommended": false
            }
          ]
        }
      ]
    },
    {
      "symbol": "CRM",
      "option_symbol": "CRM260828P00140000",
      "price": 164.11,
      "expiration": "2026-08-28",
      "dte": 37,
      "strike": 140.0,
      "bid": 1.51,
      "delta": -0.143,
      "open_interest": 64,
      "collateral": 14000.0,
      "premium": 151.0,
      "yield_30d_pct": 0.875,
      "annualized_pct": 10.64,
      "preferred": false,
      "company_name": "Salesforce, Inc.",
      "pe": 18.91,
      "week52_low": 146.32,
      "week52_high": 274.0,
      "weeklies": [
        {
          "expiration": "2026-07-24",
          "dte": 2,
          "puts": []
        },
        {
          "expiration": "2026-07-31",
          "dte": 9,
          "puts": [
            {
              "strike": 150.0,
              "bid": 1.16,
              "premium": 116.0,
              "pct_of_collateral": 0.773,
              "delta": -0.168,
              "open_interest": 618,
              "recommended": true
            }
          ]
        },
        {
          "expiration": "2026-08-07",
          "dte": 16,
          "puts": [
            {
              "strike": 145.0,
              "bid": 1.09,
              "premium": 109.0,
              "pct_of_collateral": 0.752,
              "delta": -0.135,
              "open_interest": 356,
              "recommended": true
            }
          ]
        }
      ]
    },
    {
      "symbol": "CVX",
      "option_symbol": "CVX260821P00177500",
      "price": 192.99,
      "expiration": "2026-08-21",
      "dte": 30,
      "strike": 177.5,
      "bid": 1.47,
      "delta": -0.171,
      "open_interest": 50,
      "collateral": 17750.0,
      "premium": 147.0,
      "yield_30d_pct": 0.828,
      "annualized_pct": 10.08,
      "preferred": false,
      "company_name": "Chevron Corporation",
      "pe": 33.68,
      "week52_low": 146.49,
      "week52_high": 214.71,
      "weeklies": [
        {
          "expiration": "2026-07-24",
          "dte": 2,
          "puts": [
            {
              "strike": 192.5,
              "bid": 1.35,
              "premium": 135.0,
              "pct_of_collateral": 0.701,
              "delta": -0.446,
              "open_interest": 21,
              "recommended": true
            }
          ]
        },
        {
          "expiration": "2026-07-31",
          "dte": 9,
          "puts": [
            {
              "strike": 187.5,
              "bid": 1.64,
              "premium": 164.0,
              "pct_of_collateral": 0.875,
              "delta": -0.282,
              "open_interest": 59,
              "recommended": true
            }
          ]
        },
        {
          "expiration": "2026-08-07",
          "dte": 16,
          "puts": [
            {
              "strike": 182.5,
              "bid": 1.32,
              "premium": 132.0,
              "pct_of_collateral": 0.723,
              "delta": -0.189,
              "open_interest": 23,
              "recommended": true
            },
            {
              "strike": 185.0,
              "bid": 1.76,
              "premium": 176.0,
              "pct_of_collateral": 0.951,
              "delta": -0.246,
              "open_interest": 810,
              "recommended": false
            }
          ]
        }
      ]
    },
    {
      "symbol": "COIN",
      "option_symbol": "COIN260828P00125000",
      "price": 166.66,
      "expiration": "2026-08-28",
      "dte": 37,
      "strike": 125.0,
      "bid": 1.33,
      "delta": -0.106,
      "open_interest": 53,
      "collateral": 12500.0,
      "premium": 133.0,
      "yield_30d_pct": 0.863,
      "annualized_pct": 10.5,
      "preferred": false,
      "company_name": "Coinbase Global, Inc.",
      "pe": 60.85,
      "week52_low": 139.18,
      "week52_high": 405.31,
      "weeklies": [
        {
          "expiration": "2026-07-24",
          "dte": 2,
          "puts": [
            {
              "strike": 160.0,
              "bid": 1.6,
              "premium": 160.0,
              "pct_of_collateral": 1.0,
              "delta": -0.261,
              "open_interest": 2280,
              "recommended": true
            }
          ]
        },
        {
          "expiration": "2026-07-31",
          "dte": 9,
          "puts": [
            {
              "strike": 137.0,
              "bid": 0.99,
              "premium": 99.0,
              "pct_of_collateral": 0.723,
              "delta": -0.091,
              "open_interest": 22,
              "recommended": true
            },
            {
              "strike": 138.0,
              "bid": 1.08,
              "premium": 108.0,
              "pct_of_collateral": 0.783,
              "delta": -0.098,
              "open_interest": 10,
              "recommended": false
            },
            {
              "strike": 139.0,
              "bid": 1.18,
              "premium": 118.0,
              "pct_of_collateral": 0.849,
              "delta": -0.106,
              "open_interest": 31,
              "recommended": false
            }
          ]
        },
        {
          "expiration": "2026-08-07",
          "dte": 16,
          "puts": [
            {
              "strike": 130.0,
              "bid": 1.13,
              "premium": 113.0,
              "pct_of_collateral": 0.869,
              "delta": -0.083,
              "open_interest": 277,
              "recommended": true
            }
          ]
        }
      ]
    },
    {
      "symbol": "PG",
      "option_symbol": "PG260821P00140000",
      "price": 149.2,
      "expiration": "2026-08-21",
      "dte": 30,
      "strike": 140.0,
      "bid": 1.29,
      "delta": -0.209,
      "open_interest": 2369,
      "collateral": 14000.0,
      "premium": 129.0,
      "yield_30d_pct": 0.921,
      "annualized_pct": 11.21,
      "preferred": false,
      "company_name": "The Procter & Gamble Company",
      "pe": 21.8,
      "week52_low": 137.62,
      "week52_high": 167.25,
      "weeklies": [
        {
          "expiration": "2026-07-24",
          "dte": 2,
          "puts": []
        },
        {
          "expiration": "2026-07-31",
          "dte": 9,
          "puts": [
            {
              "strike": 144.0,
              "bid": 1.22,
              "premium": 122.0,
              "pct_of_collateral": 0.847,
              "delta": -0.28,
              "open_interest": 107,
              "recommended": true
            }
          ]
        },
        {
          "expiration": "2026-08-07",
          "dte": 16,
          "puts": [
            {
              "strike": 142.0,
              "bid": 1.07,
              "premium": 107.0,
              "pct_of_collateral": 0.754,
              "delta": -0.234,
              "open_interest": 203,
              "recommended": true
            },
            {
              "strike": 143.0,
              "bid": 1.31,
              "premium": 131.0,
              "pct_of_collateral": 0.916,
              "delta": -0.269,
              "open_interest": 20,
              "recommended": false
            }
          ]
        }
      ]
    },
    {
      "symbol": "QCOM",
      "option_symbol": "QCOM260828P00130000",
      "price": 176.22,
      "expiration": "2026-08-28",
      "dte": 37,
      "strike": 130.0,
      "bid": 1.26,
      "delta": -0.079,
      "open_interest": 110,
      "collateral": 13000.0,
      "premium": 126.0,
      "yield_30d_pct": 0.786,
      "annualized_pct": 9.56,
      "preferred": false,
      "company_name": "QUALCOMM Incorporated",
      "pe": 18.88,
      "week52_low": 121.99,
      "week52_high": 259.92,
      "weeklies": [
        {
          "expiration": "2026-07-24",
          "dte": 2,
          "puts": [
            {
              "strike": 170.0,
              "bid": 1.66,
              "premium": 166.0,
              "pct_of_collateral": 0.976,
              "delta": -0.262,
              "open_interest": 1524,
              "recommended": true
            }
          ]
        },
        {
          "expiration": "2026-07-31",
          "dte": 9,
          "puts": [
            {
              "strike": 146.0,
              "bid": 1.05,
              "premium": 105.0,
              "pct_of_collateral": 0.719,
              "delta": -0.093,
              "open_interest": 13,
              "recommended": true
            },
            {
              "strike": 147.0,
              "bid": 1.2,
              "premium": 120.0,
              "pct_of_collateral": 0.816,
              "delta": -0.1,
              "open_interest": 38,
              "recommended": false
            },
            {
              "strike": 148.0,
              "bid": 1.33,
              "premium": 133.0,
              "pct_of_collateral": 0.899,
              "delta": -0.108,
              "open_interest": 37,
              "recommended": false
            }
          ]
        },
        {
          "expiration": "2026-08-07",
          "dte": 16,
          "puts": [
            {
              "strike": 140.0,
              "bid": 1.15,
              "premium": 115.0,
              "pct_of_collateral": 0.821,
              "delta": -0.083,
              "open_interest": 204,
              "recommended": true
            }
          ]
        }
      ]
    },
    {
      "symbol": "BABA",
      "option_symbol": "BABA260828P00100000",
      "price": 116.52,
      "expiration": "2026-08-28",
      "dte": 37,
      "strike": 100.0,
      "bid": 1.15,
      "delta": -0.142,
      "open_interest": 192,
      "collateral": 10000.0,
      "premium": 115.0,
      "yield_30d_pct": 0.932,
      "annualized_pct": 11.34,
      "preferred": false,
      "company_name": "Alibaba Group Holding Limited",
      "pe": 17.99,
      "week52_low": 91.99,
      "week52_high": 192.67,
      "weeklies": [
        {
          "expiration": "2026-07-24",
          "dte": 2,
          "puts": [
            {
              "strike": 115.0,
              "bid": 1.11,
              "premium": 111.0,
              "pct_of_collateral": 0.965,
              "delta": -0.358,
              "open_interest": 1876,
              "recommended": true
            }
          ]
        },
        {
          "expiration": "2026-07-31",
          "dte": 9,
          "puts": [
            {
              "strike": 110.0,
              "bid": 0.87,
              "premium": 87.0,
              "pct_of_collateral": 0.791,
              "delta": -0.201,
              "open_interest": 1207,
              "recommended": true
            }
          ]
        },
        {
          "expiration": "2026-08-07",
          "dte": 16,
          "puts": [
            {
              "strike": 108.0,
              "bid": 1.07,
              "premium": 107.0,
              "pct_of_collateral": 0.991,
              "delta": -0.193,
              "open_interest": 182,
              "recommended": true
            }
          ]
        }
      ]
    },
    {
      "symbol": "CSCO",
      "option_symbol": "CSCO260828P00095000",
      "price": 113.22,
      "expiration": "2026-08-28",
      "dte": 37,
      "strike": 95.0,
      "bid": 1.11,
      "delta": -0.134,
      "open_interest": 55,
      "collateral": 9500.0,
      "premium": 111.0,
      "yield_30d_pct": 0.947,
      "annualized_pct": 11.53,
      "preferred": false,
      "company_name": "Cisco Systems, Inc.",
      "pe": 37.4,
      "week52_low": 65.75,
      "week52_high": 130.37,
      "weeklies": [
        {
          "expiration": "2026-07-24",
          "dte": 2,
          "puts": [
            {
              "strike": 112.0,
              "bid": 1.05,
              "premium": 105.0,
              "pct_of_collateral": 0.938,
              "delta": -0.375,
              "open_interest": 590,
              "recommended": true
            }
          ]
        },
        {
          "expiration": "2026-07-31",
          "dte": 9,
          "puts": [
            {
              "strike": 108.0,
              "bid": 0.95,
              "premium": 95.0,
              "pct_of_collateral": 0.88,
              "delta": -0.23,
              "open_interest": 488,
              "recommended": true
            }
          ]
        },
        {
          "expiration": "2026-08-07",
          "dte": 16,
          "puts": [
            {
              "strike": 104.0,
              "bid": 0.84,
              "premium": 84.0,
              "pct_of_collateral": 0.808,
              "delta": -0.167,
              "open_interest": 159,
              "recommended": true
            },
            {
              "strike": 105.0,
              "bid": 1.03,
              "premium": 103.0,
              "pct_of_collateral": 0.981,
              "delta": -0.191,
              "open_interest": 105,
              "recommended": false
            }
          ]
        }
      ]
    },
    {
      "symbol": "C",
      "option_symbol": "C260828P00120000",
      "price": 132.35,
      "expiration": "2026-08-28",
      "dte": 37,
      "strike": 120.0,
      "bid": 1.11,
      "delta": -0.165,
      "open_interest": 213,
      "collateral": 12000.0,
      "premium": 111.0,
      "yield_30d_pct": 0.75,
      "annualized_pct": 9.13,
      "preferred": false,
      "company_name": "Citigroup Inc.",
      "pe": 14.24,
      "week52_low": 87.94,
      "week52_high": 147.96,
      "weeklies": [
        {
          "expiration": "2026-07-24",
          "dte": 2,
          "puts": [
            {
              "strike": 132.0,
              "bid": 1.07,
              "premium": 107.0,
              "pct_of_collateral": 0.811,
              "delta": -0.456,
              "open_interest": 550,
              "recommended": true
            }
          ]
        },
        {
          "expiration": "2026-07-31",
          "dte": 9,
          "puts": [
            {
              "strike": 129.0,
              "bid": 1.09,
              "premium": 109.0,
              "pct_of_collateral": 0.845,
              "delta": -0.291,
              "open_interest": 154,
              "recommended": true
            }
          ]
        },
        {
          "expiration": "2026-08-07",
          "dte": 16,
          "puts": [
            {
              "strike": 125.0,
              "bid": 1.03,
              "premium": 103.0,
              "pct_of_collateral": 0.824,
              "delta": -0.208,
              "open_interest": 202,
              "recommended": true
            },
            {
              "strike": 126.0,
              "bid": 1.21,
              "premium": 121.0,
              "pct_of_collateral": 0.96,
              "delta": -0.241,
              "open_interest": 62,
              "recommended": false
            }
          ]
        }
      ]
    },
    {
      "symbol": "WMT",
      "option_symbol": "WMT260828P00101000",
      "price": 109.36,
      "expiration": "2026-08-28",
      "dte": 37,
      "strike": 101.0,
      "bid": 1.1,
      "delta": -0.195,
      "open_interest": 5125,
      "collateral": 10100.0,
      "premium": 110.0,
      "yield_30d_pct": 0.883,
      "annualized_pct": 10.74,
      "preferred": false,
      "company_name": "Walmart Inc.",
      "pe": 38.5,
      "week52_low": 95.29,
      "week52_high": 135.16,
      "weeklies": [
        {
          "expiration": "2026-07-24",
          "dte": 2,
          "puts": []
        },
        {
          "expiration": "2026-07-31",
          "dte": 9,
          "puts": [
            {
              "strike": 108.0,
              "bid": 1.02,
              "premium": 102.0,
              "pct_of_collateral": 0.944,
              "delta": -0.361,
              "open_interest": 1515,
              "recommended": true
            }
          ]
        },
        {
          "expiration": "2026-08-07",
          "dte": 16,
          "puts": [
            {
              "strike": 106.0,
              "bid": 0.92,
              "premium": 92.0,
              "pct_of_collateral": 0.868,
              "delta": -0.265,
              "open_interest": 432,
              "recommended": true
            }
          ]
        }
      ]
    },
    {
      "symbol": "ORCL",
      "option_symbol": "ORCL260828P00095000",
      "price": 126.6,
      "expiration": "2026-08-28",
      "dte": 37,
      "strike": 95.0,
      "bid": 1.05,
      "delta": -0.088,
      "open_interest": 342,
      "collateral": 9500.0,
      "premium": 105.0,
      "yield_30d_pct": 0.896,
      "annualized_pct": 10.9,
      "preferred": true,
      "company_name": "Oracle Corporation",
      "pe": 21.58,
      "week52_low": 120.03,
      "week52_high": 345.72,
      "weeklies": [
        {
          "expiration": "2026-07-24",
          "dte": 2,
          "puts": [
            {
              "strike": 120.0,
              "bid": 0.87,
              "premium": 87.0,
              "pct_of_collateral": 0.725,
              "delta": -0.206,
              "open_interest": 4843,
              "recommended": true
            },
            {
              "strike": 121.0,
              "bid": 1.1,
              "premium": 110.0,
              "pct_of_collateral": 0.909,
              "delta": -0.247,
              "open_interest": 694,
              "recommended": false
            }
          ]
        },
        {
          "expiration": "2026-07-31",
          "dte": 9,
          "puts": [
            {
              "strike": 110.0,
              "bid": 0.78,
              "premium": 78.0,
              "pct_of_collateral": 0.709,
              "delta": -0.112,
              "open_interest": 1955,
              "recommended": true
            },
            {
              "strike": 111.0,
              "bid": 0.9,
              "premium": 90.0,
              "pct_of_collateral": 0.811,
              "delta": -0.126,
              "open_interest": 340,
              "recommended": false
            },
            {
              "strike": 112.0,
              "bid": 0.86,
              "premium": 86.0,
              "pct_of_collateral": 0.768,
              "delta": -0.142,
              "open_interest": 232,
              "recommended": false
            }
          ]
        },
        {
          "expiration": "2026-08-07",
          "dte": 16,
          "puts": [
            {
              "strike": 105.0,
              "bid": 0.91,
              "premium": 91.0,
              "pct_of_collateral": 0.867,
              "delta": -0.101,
              "open_interest": 690,
              "recommended": true
            }
          ]
        }
      ]
    },
    {
      "symbol": "PLTR",
      "option_symbol": "PLTR260821P00095000",
      "price": 124.62,
      "expiration": "2026-08-21",
      "dte": 30,
      "strike": 95.0,
      "bid": 0.94,
      "delta": -0.079,
      "open_interest": 3191,
      "collateral": 9500.0,
      "premium": 94.0,
      "yield_30d_pct": 0.989,
      "annualized_pct": 12.04,
      "preferred": false,
      "company_name": "Palantir Technologies Inc.",
      "pe": 139.97,
      "week52_low": 106.37,
      "week52_high": 207.52,
      "weeklies": [
        {
          "expiration": "2026-07-24",
          "dte": 2,
          "puts": [
            {
              "strike": 120.0,
              "bid": 0.87,
              "premium": 87.0,
              "pct_of_collateral": 0.725,
              "delta": -0.228,
              "open_interest": 4874,
              "recommended": true
            },
            {
              "strike": 121.0,
              "bid": 1.1,
              "premium": 110.0,
              "pct_of_collateral": 0.909,
              "delta": -0.277,
              "open_interest": 1680,
              "recommended": false
            }
          ]
        },
        {
          "expiration": "2026-07-31",
          "dte": 9,
          "puts": [
            {
              "strike": 113.0,
              "bid": 0.88,
              "premium": 88.0,
              "pct_of_collateral": 0.779,
              "delta": -0.143,
              "open_interest": 405,
              "recommended": true
            },
            {
              "strike": 114.0,
              "bid": 0.98,
              "premium": 98.0,
              "pct_of_collateral": 0.86,
              "delta": -0.163,
              "open_interest": 663,
              "recommended": false
            }
          ]
        },
        {
          "expiration": "2026-08-07",
          "dte": 16,
          "puts": [
            {
              "strike": 100.0,
              "bid": 0.9,
              "premium": 90.0,
              "pct_of_collateral": 0.9,
              "delta": -0.087,
              "open_interest": 1903,
              "recommended": true
            },
            {
              "strike": 101.0,
              "bid": 1.0,
              "premium": 100.0,
              "pct_of_collateral": 0.99,
              "delta": -0.095,
              "open_interest": 78,
              "recommended": false
            }
          ]
        }
      ]
    },
    {
      "symbol": "TGT",
      "option_symbol": "TGT260814P00128000",
      "price": 139.0,
      "expiration": "2026-08-14",
      "dte": 23,
      "strike": 128.0,
      "bid": 0.94,
      "delta": -0.179,
      "open_interest": 282,
      "collateral": 12800.0,
      "premium": 94.0,
      "yield_30d_pct": 0.958,
      "annualized_pct": 11.65,
      "preferred": false,
      "company_name": "Target Corporation",
      "pe": 18.22,
      "week52_low": 83.44,
      "week52_high": 144.4,
      "weeklies": [
        {
          "expiration": "2026-07-24",
          "dte": 2,
          "puts": [
            {
              "strike": 138.0,
              "bid": 1.31,
              "premium": 131.0,
              "pct_of_collateral": 0.949,
              "delta": -0.445,
              "open_interest": 517,
              "recommended": true
            }
          ]
        },
        {
          "expiration": "2026-07-31",
          "dte": 9,
          "puts": [
            {
              "strike": 134.0,
              "bid": 0.96,
              "premium": 96.0,
              "pct_of_collateral": 0.716,
              "delta": -0.254,
              "open_interest": 74,
              "recommended": true
            },
            {
              "strike": 135.0,
              "bid": 1.22,
              "premium": 122.0,
              "pct_of_collateral": 0.904,
              "delta": -0.3,
              "open_interest": 69,
              "recommended": false
            }
          ]
        },
        {
          "expiration": "2026-08-07",
          "dte": 16,
          "puts": [
            {
              "strike": 132.0,
              "bid": 1.1,
              "premium": 110.0,
              "pct_of_collateral": 0.833,
              "delta": -0.229,
              "open_interest": 23,
              "recommended": true
            }
          ]
        }
      ]
    },
    {
      "symbol": "KO",
      "option_symbol": "KO260828P00079000",
      "price": 82.14,
      "expiration": "2026-08-28",
      "dte": 37,
      "strike": 79.0,
      "bid": 0.87,
      "delta": -0.267,
      "open_interest": 60,
      "collateral": 7900.0,
      "premium": 87.0,
      "yield_30d_pct": 0.893,
      "annualized_pct": 10.86,
      "preferred": false,
      "company_name": "The Coca-Cola Company",
      "pe": 25.85,
      "week52_low": 65.35,
      "week52_high": 85.68,
      "weeklies": [
        {
          "expiration": "2026-07-24",
          "dte": 2,
          "puts": []
        },
        {
          "expiration": "2026-07-31",
          "dte": 9,
          "puts": [
            {
              "strike": 81.0,
              "bid": 0.79,
              "premium": 79.0,
              "pct_of_collateral": 0.975,
              "delta": -0.356,
              "open_interest": 271,
              "recommended": true
            }
          ]
        },
        {
          "expiration": "2026-08-07",
          "dte": 16,
          "puts": [
            {
              "strike": 80.0,
              "bid": 0.72,
              "premium": 72.0,
              "pct_of_collateral": 0.9,
              "delta": -0.287,
              "open_interest": 236,
              "recommended": true
            }
          ]
        }
      ]
    },
    {
      "symbol": "ABNB",
      "option_symbol": "ABNB260821P00120000",
      "price": 140.05,
      "expiration": "2026-08-21",
      "dte": 30,
      "strike": 120.0,
      "bid": 0.86,
      "delta": -0.115,
      "open_interest": 631,
      "collateral": 12000.0,
      "premium": 86.0,
      "yield_30d_pct": 0.717,
      "annualized_pct": 8.72,
      "preferred": false,
      "company_name": "Airbnb, Inc.",
      "pe": 34.58,
      "week52_low": 110.81,
      "week52_high": 150.88,
      "weeklies": [
        {
          "expiration": "2026-07-24",
          "dte": 2,
          "puts": [
            {
              "strike": 139.0,
              "bid": 0.99,
              "premium": 99.0,
              "pct_of_collateral": 0.712,
              "delta": -0.396,
              "open_interest": 65,
              "recommended": true
            },
            {
              "strike": 140.0,
              "bid": 1.39,
              "premium": 139.0,
              "pct_of_collateral": 0.993,
              "delta": -0.488,
              "open_interest": 100,
              "recommended": false
            }
          ]
        },
        {
          "expiration": "2026-07-31",
          "dte": 9,
          "puts": [
            {
              "strike": 136.0,
              "bid": 1.19,
              "premium": 119.0,
              "pct_of_collateral": 0.875,
              "delta": -0.293,
              "open_interest": 215,
              "recommended": true
            }
          ]
        },
        {
          "expiration": "2026-08-07",
          "dte": 16,
          "puts": [
            {
              "strike": 125.0,
              "bid": 1.09,
              "premium": 109.0,
              "pct_of_collateral": 0.872,
              "delta": -0.146,
              "open_interest": 351,
              "recommended": true
            }
          ]
        }
      ]
    },
    {
      "symbol": "WFC",
      "option_symbol": "WFC260828P00081000",
      "price": 86.68,
      "expiration": "2026-08-28",
      "dte": 37,
      "strike": 81.0,
      "bid": 0.82,
      "delta": -0.212,
      "open_interest": 60,
      "collateral": 8100.0,
      "premium": 82.0,
      "yield_30d_pct": 0.821,
      "annualized_pct": 9.99,
      "preferred": false,
      "company_name": "Wells Fargo & Company",
      "pe": 12.56,
      "week52_low": 72.78,
      "week52_high": 97.76,
      "weeklies": [
        {
          "expiration": "2026-07-24",
          "dte": 2,
          "puts": []
        },
        {
          "expiration": "2026-07-31",
          "dte": 9,
          "puts": [
            {
              "strike": 85.0,
              "bid": 0.75,
              "premium": 75.0,
              "pct_of_collateral": 0.882,
              "delta": -0.314,
              "open_interest": 1291,
              "recommended": true
            }
          ]
        },
        {
          "expiration": "2026-08-07",
          "dte": 16,
          "puts": [
            {
              "strike": 83.0,
              "bid": 0.7,
              "premium": 70.0,
              "pct_of_collateral": 0.843,
              "delta": -0.237,
              "open_interest": 888,
              "recommended": true
            }
          ]
        }
      ]
    }
  ],
  "indices": [
    {
      "label": "S&P 500",
      "value": 7498.96,
      "change_pct": -0.14
    },
    {
      "label": "Dow Jones",
      "value": 52219.0,
      "change_pct": -0.01
    },
    {
      "label": "Nasdaq 100",
      "value": 28998.1,
      "change_pct": -0.54
    }
  ]
}